Workbook

Sheet Overview
A1: Sr | B1: MODULE | C1: DESCRIPTION | D1: REQUIRED | E1: PRIORITY | F1: COMMENTS
A2: PATIENT MOBILE APP (native iOS & Android)
A3: 1 | B3: Onboarding & consent | C3: Account creation, identity verification, two-factor login, and plain-language consent captured before any data is collected. | D3: Yes | E3: Must Have
A4: 2 | B4: Intake & goals | C4: An AI-guided intake gathers goals, history and habits, then proposes goals the patient selects — which stay pending physician approval. | D4: Yes | E4: Must Have
A5: 3 | B5: Data connections | C5: The patient authorizes their EMR (across multiple hospitals), connects wearables via Terra, and uploads outside lab or DEXA reports. | D5: Yes | E5: Must Have
A6: 4 | B6: Dashboard & record | C6: A near-real-time home screen showing overall and domain scores, trends, the longitudinal record, and all biomarkers on gauges. | D6: Yes | E6: Must Have
A7: 5 | B7: Optimization report | C7: The interpretive quarterly report — released only after physician sign-off — with per-marker gauges, lifestyle-vs-physician guidance, and data provenance. | D7: Yes | E7: Must Have
A8: 6 | B8: Plan & tasks | C8: The patient's daily and weekly lifestyle plan, with morning and evening check-ins and adherence logging. | D8: Yes | E8: Must Have
A9: 7 | B9: AI copilot (chat) | C9: A guarded assistant grounded in the patient's own data — answering wellness questions by text or voice, routing clinical questions to the physician, and redirecting emergencies to urgent care. | D9: Yes | E9: Must Have
A10: 8 | B10: Messages, coaching, purchases | C10: Secure care-team messaging, coaching booking, and management of membership, add-on panels and AI usage. | D10: Yes | E10: Must Have
A11: PHYSICIAN / PRACTICE PORTAL (web)
A12: 1 | B12: Roster & referral | C12: The practice's patient roster with enrollment, physician assignment, patient referral, and invitation. | D12: Yes | E12: Must Have
A13: 2 | B13: Priority queue | C13: A work queue that sorts patients by clinical rule severity, change magnitude and recency so the physician sees what needs attention first. | D13: Yes | E13: Must Have
A14: 3 | B14: One-page summary & record | C14: A single-screen patient summary plus the full longitudinal record with provenance, and a pre-visit brief of changes since the last visit. | D14: Yes | E14: Must Have
A15: 4 | B15: AI copilot | C15: A physician-facing copilot that surfaces biomarker trends, flags findings, suggests follow-up tests, and highlights panel-level gaps. | D15: Yes | E15: Must Have
A16: 5 | B16: Report review & sign-off | C16: Where the physician reviews the AI-drafted report and approves, edits, rejects or requests a repeat test — sign-off releases it to the patient. | D16: Yes | E16: Must Have
A17: 6 | B17: Plan builder | C17: Tools to set goals, interventions, monitoring cadence and success measures, and to approve the patient's goals. | D17: Yes | E17: Must Have
A18: 7 | B18: Alerts & safety | C18: Alert detail with triggering data, rule version and confidence, and the workflow to acknowledge and route abnormal findings. | D18: Yes | E18: Must Have
A19: 8 | B19: Billing & admin | C19: Practice billing and revenue-share visibility, plus user, role and permission management. | D19: Yes | E19: Must Have
A20: 9 | B20: Practice dashboard | C20: A practice-scoped analytics view of enrollment, engagement, outcomes, physician review time and renewal-supporting metrics. | D20: Yes | E20: Must Have
A21: COACH PORTAL
A22: 1 | B22: Access | C22: Secure login with MFA and tightly scoped access — coaches see only wellness data for their assigned patients, never the clinical record. | D22: Yes | E22: Must Have
A23: 2 | B23: Patient context | C23: The coach's view of each assigned patient's physician-approved goals, lifestyle plan and adherence. | D23: Yes | E23: Must Have
A24: 3 | B24: Scheduling | C24: Tools for the coach to view and manage coaching sessions and set their availability. | D24: Yes | E24: Must Have
A25: 4 | B25: Messaging | C25: Secure messaging with assigned patients, kept within the wellness boundary — no clinical advice. | D25: Yes | E25: Must Have
A26: 5 | B26: Session notes | C26: Recording and reviewing coaching session notes per patient. | D26: Yes | E26: Must Have
A27: HOL TEAM PORTAL (web)
A28: 1 | B28: Clinical content — biomarker catalog | C28: Maintaining the 125-biomarker catalog, keeping lab range, physician target and HOL optimal range as three separate fields. | D28: Yes | E28: Must Have
A29: 2 | B29: Clinical content — protocols & rules | C29: Authoring and versioning the protocol/SOP library and configuring the alert rules and score weights the engine uses. | D29: Yes | E29: Must Have
A30: 3 | B30: Clinical content — evaluation harness | C30: A library of graded clinical test cases that every AI change is regression-tested against, with prompt/model versions logged. | D30: Yes | E30: Must Have
A31: 4 | B31: Operations — integration health | C31: Monitoring the health of EMR, Terra and partner connections, and surfacing and retrying failed imports. | D31: Yes | E31: Must Have
A32: 5 | B32: Operations — parsing review | C32: A verification queue where HOL staff review and correct low-confidence document extractions before they enter the record. | D32: Yes | E32: Must Have
A33: 6 | B33: Operations — consent, audit, tenancy | C33: Consent status per patient, the immutable audit trail, and tenant and security administration. | D33: Yes | E33: Must Have
A34: 7 | B34: Back office & catalog | C34: Managing the add-on catalog and pricing, tracking partner commissions, and administering usage, billing and revenue-share. | D34: Yes | E34: Must Have
A35: 8 | B35: Analytics dashboards | C35: HOL-wide, cross-practice dashboards for engagement, outcomes, care gaps and program value. | D35: Yes | E35: Must Have
A36: SHARED BACKEND (spans all portals)
A37: 1 | B37: LHOR / longitudinal record | C37: The normalization pipeline and time-series database that turn every source into one comparable per-patient record, plus the document store and full data model. | D37: Yes | E37: Must Have
A38: 2 | B38: AI intelligence layer | C38: Retrieval on a commercial model with orchestration, grounding, report and digest generation, the guarded chat and physician copilot, guardrails and the evaluation harness. | D38: Yes | E38: Must Have
A39: 3 | B39: CRM / care orchestration | C39: The workflow engine running the care loop, physician sign-off routing, abnormal-finding routing, engagement automation, scoring and the alert/rules engine. | D39: Yes | E39: Must Have
A40: 4 | B40: Identity & multi-tenancy | C40: Authentication for all roles, role-based access control, and isolation of each practice's data as its own tenant. | D40: Yes | E40: Must Have
A41: 5 | B41: Notifications (delivery engine) | C41: The shared push, email and SMS delivery service that carries only alerts prompting the user to open the app — never PHI. | D41: Yes | E41: Must Have
A42: 6 | B42: Platform foundations — security | C42: Encryption, immutable audit logging, backups and DR, SOC 2 posture, and retention/deletion — spanning every surface. | D42: Yes | E42: Must Have
A43: INTEGRATIONS
B44: Practice EMR | C44: Epic, Athena | D44: Yes | E44: Must Have
B45: Werables | C45: Terra | D45: Yes | E45: Must Have
B46: DEXA | C46: BodySpec/ Fitnescity | D46: Yes | E46: Must Have
B47: AI model | C47: OpenAI / Anthropic | D47: Yes | E47: Must Have
B48: Payments | C48: Stripe | D48: Yes | E48: Must Have
B49: Cloud & storage (AWS) | C49: AWS | D49: Yes | E49: Must Have
B50: Labs | C50: Quest | D50: Yes | E50: Must Have

Sheet Deviation 30-10-2026
A1: Module | B1: Sub-module | C1: Status | D1: Description | E1: Required | F1: FE | G1: BE | H1: Approved
A2: SECTION A: NEW AND MODIFIED FEATURES BY PORTAL
A3: SUPER ADMIN PORTAL
A4: Super Admin Portal: New Features
A5: =TRIM('Super Admin Portal Hol Portal'!A10) | B5: =IFERROR(__xludf.DUMMYFUNCTION("IFERROR(TEXTJOIN("", "",TRUE,UNIQUE(FILTER(TRIM('Super Admin Portal Hol Portal'!B11:B22),'Super Admin Portal Hol Portal'!E11:E22=""New""))),"""")"),"Navigation, Dashboard") | C5: New | D5: =IFERROR(__xludf.DUMMYFUNCTION("IFERROR(TEXTJOIN(CHAR(10),TRUE,FILTER(""• ""&TRIM('Super Admin Portal Hol Portal'!C11:C22),'Super Admin Portal Hol Portal'!E11:E22=""New"")),"""")"),"• Navigation & Notifications • Global Search • Dashboard Filters • Summary Cards • Enrolment by State • Invites & Conversion • Patient Status & Enrolment Funnel • Practices on Inlay • Region Table") | E5: Yes | F5: =SUMIFS('Super Admin Portal Hol Portal'!G11:G22,'Super Admin Portal Hol Portal'!E11:E22,"New") | G5: =SUMIFS('Super Admin Portal Hol Portal'!H11:H22,'Super Admin Portal Hol Portal'!E11:E22,"New")
A6: =TRIM('Super Admin Portal Hol Portal'!A23) | B6: =IFERROR(__xludf.DUMMYFUNCTION("IFERROR(TEXTJOIN("", "",TRUE,UNIQUE(FILTER(TRIM('Super Admin Portal Hol Portal'!B24:B41),'Super Admin Portal Hol Portal'!E24:E41=""New""))),"""")"),"Clinical Content, Catalog, Rules, Eval") | C6: New | D6: =IFERROR(__xludf.DUMMYFUNCTION("IFERROR(TEXTJOIN(CHAR(10),TRUE,FILTER(""• ""&TRIM('Super Admin Portal Hol Portal'!C24:C41),'Super Admin Portal Hol Portal'!E24:E41=""New"")),"""")"),"• Clinical Content Overview • Range List • Sex/Age Rule List • Alert Rule List • Test-Case List") | E6: Yes | F6: =SUMIFS('Super Admin Portal Hol Portal'!G24:G41,'Super Admin Portal Hol Portal'!E24:E41,"New") | G6: =SUMIFS('Super Admin Portal Hol Portal'!H24:H41,'Super Admin Portal Hol Portal'!E24:E41,"New")
A7: =TRIM('Super Admin Portal Hol Portal'!A42) | B7: =IFERROR(__xludf.DUMMYFUNCTION("IFERROR(TEXTJOIN("", "",TRUE,UNIQUE(FILTER(TRIM('Super Admin Portal Hol Portal'!B43:B54),'Super Admin Portal Hol Portal'!E43:E54=""New""))),"""")"),"Settings, AI, Partners") | C7: New | D7: =IFERROR(__xludf.DUMMYFUNCTION("IFERROR(TEXTJOIN(CHAR(10),TRUE,FILTER(""• ""&TRIM('Super Admin Portal Hol Portal'!C43:C54),'Super Admin Portal Hol Portal'!E43:E54=""New"")),"""")"),"• Settings Overview • AI Credit Allowance • Partner List • Add & Edit Partner") | E7: Yes | F7: =SUMIFS('Super Admin Portal Hol Portal'!G43:G54,'Super Admin Portal Hol Portal'!E43:E54,"New") | G7: =SUMIFS('Super Admin Portal Hol Portal'!H43:H54,'Super Admin Portal Hol Portal'!E43:E54,"New")
A8: =TRIM('Super Admin Portal Hol Portal'!A55) | B8: =IFERROR(__xludf.DUMMYFUNCTION("IFERROR(TEXTJOIN("", "",TRUE,UNIQUE(FILTER(TRIM('Super Admin Portal Hol Portal'!B56:B60),'Super Admin Portal Hol Portal'!E56:E60=""New""))),"""")"),"Practice List, Practice Details") | C8: New | D8: =IFERROR(__xludf.DUMMYFUNCTION("IFERROR(TEXTJOIN(CHAR(10),TRUE,FILTER(""• ""&TRIM('Super Admin Portal Hol Portal'!C56:C60),'Super Admin Portal Hol Portal'!E56:E60=""New"")),"""")"),"• Practice List • Practice Overview • Edit & Deactivate Practice • Providers & Users") | E8: Yes | F8: =SUMIFS('Super Admin Portal Hol Portal'!G56:G60,'Super Admin Portal Hol Portal'!E56:E60,"New") | G8: =SUMIFS('Super Admin Portal Hol Portal'!H56:H60,'Super Admin Portal Hol Portal'!E56:E60,"New")
A9: =TRIM('Super Admin Portal Hol Portal'!A67) | B9: =IFERROR(__xludf.DUMMYFUNCTION("IFERROR(TEXTJOIN("", "",TRUE,UNIQUE(FILTER(TRIM('Super Admin Portal Hol Portal'!B68:B80),'Super Admin Portal Hol Portal'!E68:E80=""New""))),"""")"),"Billing") | C9: New | D9: =IFERROR(__xludf.DUMMYFUNCTION("IFERROR(TEXTJOIN(CHAR(10),TRUE,FILTER(""• ""&TRIM('Super Admin Portal Hol Portal'!C68:C80),'Super Admin Portal Hol Portal'!E68:E80=""New"")),"""")"),"• Billing Dashboard • Test & Imaging Catalogue • Price & Margin Calculation • Membership & AI Allowance • Practice Billing Terms • Practice Invoices • Sales Tax") | E9: Yes | F9: =SUMIFS('Super Admin Portal Hol Portal'!G68:G80,'Super Admin Portal Hol Portal'!E68:E80,"New") | G9: =SUMIFS('Super Admin Portal Hol Portal'!H68:H80,'Super Admin Portal Hol Portal'!E68:E80,"New")
D10: Subtotal: Super Admin Portal: New Features | F10: =SUM(F5:F9) | G10: =SUM(G5:G9)
A12: Super Admin Portal: Modified Features (delta hours)
A13: =TRIM('Super Admin Portal Hol Portal'!A23) | B13: =IFERROR(__xludf.DUMMYFUNCTION("IFERROR(TEXTJOIN("", "",TRUE,UNIQUE(FILTER(TRIM('Super Admin Portal Hol Portal'!B24:B41),'Super Admin Portal Hol Portal'!E24:E41=""Modified""))),"""")"),"Catalog, Rules") | C13: Modified | D13: =IFERROR(__xludf.DUMMYFUNCTION("IFERROR(TEXTJOIN(CHAR(10),TRUE,FILTER(""• ""&TRIM('Super Admin Portal Hol Portal'!C24:C41)&"": ""&TRIM('Super Admin Portal Hol Portal'!D24:D41),'Super Admin Portal Hol Portal'!E24:E41=""Modified"")),"""")"),"• Biomarker definitions: As a clinical admin, I can maintain biomarker definitions and canonical units by adding, editing, search, filter and retiring biomarkers. • Alert rules: As a clinical admin, I can configure the deterministic safety/priority rules "&"by adding and editing rules and turning each one on or off.") | E13: Yes | F13: =SUMIFS('Super Admin Portal Hol Portal'!G24:G41,'Super Admin Portal Hol Portal'!E24:E41,"Modified")-8 | G13: =SUMIFS('Super Admin Portal Hol Portal'!H24:H41,'Super Admin Portal Hol Portal'!E24:E41,"Modified")-12
A14: =TRIM('Super Admin Portal Hol Portal'!A55) | B14: =IFERROR(__xludf.DUMMYFUNCTION("IFERROR(TEXTJOIN("", "",TRUE,UNIQUE(FILTER(TRIM('Super Admin Portal Hol Portal'!B56:B60),'Super Admin Portal Hol Portal'!E56:E60=""Modified""))),"""")"),"Tenancy") | C14: Modified | D14: =IFERROR(__xludf.DUMMYFUNCTION("IFERROR(TEXTJOIN(CHAR(10),TRUE,FILTER(""• ""&TRIM('Super Admin Portal Hol Portal'!C56:C60)&"": ""&TRIM('Super Admin Portal Hol Portal'!D56:D60),'Super Admin Portal Hol Portal'!E56:E60=""Modified"")),"""")"),"• Tenant admin: As a Super Admin, I should be able to add a practice (a new tenant) with its details, contact, location, messaging number and the features it can use.") | E14: Yes | F14: =SUMIFS('Super Admin Portal Hol Portal'!G56:G60,'Super Admin Portal Hol Portal'!E56:E60,"Modified")-2 | G14: =SUMIFS('Super Admin Portal Hol Portal'!H56:H60,'Super Admin Portal Hol Portal'!E56:E60,"Modified")-4
A15: =TRIM('Super Admin Portal Hol Portal'!A67) | B15: =IFERROR(__xludf.DUMMYFUNCTION("IFERROR(TEXTJOIN("", "",TRUE,UNIQUE(FILTER(TRIM('Super Admin Portal Hol Portal'!B68:B80),'Super Admin Portal Hol Portal'!E68:E80=""Modified""))),"""")"),"Billing") | C15: Modified | D15: =IFERROR(__xludf.DUMMYFUNCTION("IFERROR(TEXTJOIN(CHAR(10),TRUE,FILTER(""• ""&TRIM('Super Admin Portal Hol Portal'!C68:C80)&"": ""&TRIM('Super Admin Portal Hol Portal'!D68:D80),'Super Admin Portal Hol Portal'!E68:E80=""Modified"")),"""")"),"• Refunds & adjustments: As HOL ops, I can issue refunds to the original payment method, apply credits for orders that didn’t complete, and make billing adjustments. • Billing reports: As HOL ops, I can produce billing and revenue reports, including vendo"&"r payouts, revenue by lab and imaging, cancellation and late-fee losses, overdue practices, and totals by channel.") | E15: Yes | F15: =SUMIFS('Super Admin Portal Hol Portal'!G68:G80,'Super Admin Portal Hol Portal'!E68:E80,"Modified")-4 | G15: =SUMIFS('Super Admin Portal Hol Portal'!H68:H80,'Super Admin Portal Hol Portal'!E68:E80,"Modified")-8
D16: Subtotal: Super Admin Portal: Modified Features (delta hours) | F16: =SUM(F13:F15) | G16: =SUM(G13:G15)
A18: PHYSICIAN PORTAL
A19: Physician Portal: New Features
A20: =TRIM('Physician Portal Provider port'!A3) | B20: =IFERROR(__xludf.DUMMYFUNCTION("IFERROR(TEXTJOIN("", "",TRUE,UNIQUE(FILTER(TRIM('Physician Portal Provider port'!B4:B9),'Physician Portal Provider port'!E4:E9=""New""))),"""")"),"Invitation, Activate Account, Forgot Password") | C20: New | D20: =IFERROR(__xludf.DUMMYFUNCTION("IFERROR(TEXTJOIN(CHAR(10),TRUE,FILTER(""• ""&TRIM('Physician Portal Provider port'!C4:C9),'Physician Portal Provider port'!E4:E9=""New"")),"""")"),"• Invitation Email • Two-Factor Setup • Forgot Password & Reset Code") | E20: Yes | F20: =SUMIFS('Physician Portal Provider port'!G4:G9,'Physician Portal Provider port'!E4:E9,"New") | G20: =SUMIFS('Physician Portal Provider port'!H4:H9,'Physician Portal Provider port'!E4:E9,"New")
A21: =TRIM('Physician Portal Provider port'!A10) | B21: =IFERROR(__xludf.DUMMYFUNCTION("IFERROR(TEXTJOIN("", "",TRUE,UNIQUE(FILTER(TRIM('Physician Portal Provider port'!B11:B19),'Physician Portal Provider port'!E11:E19=""New""))),"""")"),"Dashboard, Worklist") | C21: New | D21: =IFERROR(__xludf.DUMMYFUNCTION("IFERROR(TEXTJOIN(CHAR(10),TRUE,FILTER(""• ""&TRIM('Physician Portal Provider port'!C11:C19),'Physician Portal Provider port'!E11:E19=""New"")),"""")"),"• My Tasks • Today’s Schedule • Abnormal Results") | E21: Yes | F21: =SUMIFS('Physician Portal Provider port'!G11:G19,'Physician Portal Provider port'!E11:E19,"New") | G21: =SUMIFS('Physician Portal Provider port'!H11:H19,'Physician Portal Provider port'!E11:E19,"New")
A22: =TRIM('Physician Portal Provider port'!A20) | B22: =IFERROR(__xludf.DUMMYFUNCTION("IFERROR(TEXTJOIN("", "",TRUE,UNIQUE(FILTER(TRIM('Physician Portal Provider port'!B21:B33),'Physician Portal Provider port'!E21:E33=""New""))),"""")"),"Add Patient, Edit Patient, Bulk Add Patients, Patients") | C22: New | D22: =IFERROR(__xludf.DUMMYFUNCTION("IFERROR(TEXTJOIN(CHAR(10),TRUE,FILTER(""• ""&TRIM('Physician Portal Provider port'!C21:C33),'Physician Portal Provider port'!E21:E33=""New"")),"""")"),"• Add Patient Form • Duplicate Patient Check • Edit Patient • Template & Upload • Add bulk patient • Tabs, Search, Filters & Pagination • Select & Export") | E22: Yes | F22: =SUMIFS('Physician Portal Provider port'!G21:G33,'Physician Portal Provider port'!E21:E33,"New") | G22: =SUMIFS('Physician Portal Provider port'!H21:H33,'Physician Portal Provider port'!E21:E33,"New")
A23: =TRIM('Physician Portal Provider port'!A34) | B23: =IFERROR(__xludf.DUMMYFUNCTION("IFERROR(TEXTJOIN("", "",TRUE,UNIQUE(FILTER(TRIM('Physician Portal Provider port'!B35:B39),'Physician Portal Provider port'!E35:E39=""New""))),"""")"),"Tasks, Add Task") | C23: New | D23: =IFERROR(__xludf.DUMMYFUNCTION("IFERROR(TEXTJOIN(CHAR(10),TRUE,FILTER(""• ""&TRIM('Physician Portal Provider port'!C35:C39),'Physician Portal Provider port'!E35:E39=""New"")),"""")"),"• Task List • Tabs, Search, Filter • Select Tasks • Bulk Mark Complete • Add Task") | E23: Yes | F23: =SUMIFS('Physician Portal Provider port'!G35:G39,'Physician Portal Provider port'!E35:E39,"New") | G23: =SUMIFS('Physician Portal Provider port'!H35:H39,'Physician Portal Provider port'!E35:E39,"New")
A24: =TRIM('Physician Portal Provider port'!A40) | B24: =IFERROR(__xludf.DUMMYFUNCTION("IFERROR(TEXTJOIN("", "",TRUE,UNIQUE(FILTER(TRIM('Physician Portal Provider port'!B41:B44),'Physician Portal Provider port'!E41:E44=""New""))),"""")"),"Scheduling") | C24: New | D24: =IFERROR(__xludf.DUMMYFUNCTION("IFERROR(TEXTJOIN(CHAR(10),TRUE,FILTER(""• ""&TRIM('Physician Portal Provider port'!C41:C44),'Physician Portal Provider port'!E41:E44=""New"")),"""")"),"• Appointments – Calendar View • Appointments – List View • Appointment Details & Filters") | E24: Yes | F24: =SUMIFS('Physician Portal Provider port'!G41:G44,'Physician Portal Provider port'!E41:E44,"New") | G24: =SUMIFS('Physician Portal Provider port'!H41:H44,'Physician Portal Provider port'!E41:E44,"New")
A25: =TRIM('Physician Portal Provider port'!A45) | B25: =IFERROR(__xludf.DUMMYFUNCTION("IFERROR(TEXTJOIN("", "",TRUE,UNIQUE(FILTER(TRIM('Physician Portal Provider port'!B46:B54),'Physician Portal Provider port'!E46:E54=""New""))),"""")"),"Communication, New Chat") | C25: New | D25: =IFERROR(__xludf.DUMMYFUNCTION("IFERROR(TEXTJOIN(CHAR(10),TRUE,FILTER(""• ""&TRIM('Physician Portal Provider port'!C46:C54),'Physician Portal Provider port'!E46:E54=""New"")),"""")"),"• Conversation List • Search & Filter Conversations • Conversation View • Send Message • Voice to Text • Attach & Share Documents • Reply to a Message • Reactions • Start New Chat") | E25: Yes | F25: =SUMIFS('Physician Portal Provider port'!G46:G54,'Physician Portal Provider port'!E46:E54,"New") | G25: =SUMIFS('Physician Portal Provider port'!H46:H54,'Physician Portal Provider port'!E46:E54,"New")
A26: =TRIM('Physician Portal Provider port'!A71) | B26: =IFERROR(__xludf.DUMMYFUNCTION("IFERROR(TEXTJOIN("", "",TRUE,UNIQUE(FILTER(TRIM('Physician Portal Provider port'!B72:B103),'Physician Portal Provider port'!E72:E103=""New""))),"""")"),"Patient Header, Dashboard, Overview, Care Plan, Encounters, Appointments, Diagnoses, Medications, Allergies, Patient Chart") | C26: New | D26: =IFERROR(__xludf.DUMMYFUNCTION("IFERROR(TEXTJOIN(CHAR(10),TRUE,FILTER(""• ""&TRIM('Physician Portal Provider port'!C72:C103),'Physician Portal Provider port'!E72:E103=""New"")),"""")"),"• Patient Header • Add patient Label • Important Updates • Face Sheet • Print Chart • Timeline • Edit Plan • Plan History • Revise Plan • Encounter List • Encounter view • Print & Download Encounter • Appointments • Diagnosis List • Diagnosis Details • Me"&"dications • Allergies • Vitals – Card View • Vitals – Trend View • Vitals – Table View • Lab Reports • Lab Orders • Add Lab Order • Family History • Patient Profile • Discharge or Deactivate Patient") | E26: Yes | F26: =SUMIFS('Physician Portal Provider port'!G72:G103,'Physician Portal Provider port'!E72:E103,"New") | G26: =SUMIFS('Physician Portal Provider port'!H72:H103,'Physician Portal Provider port'!E72:E103,"New")
A27: =TRIM('Physician Portal Provider port'!A110) | B27: =IFERROR(__xludf.DUMMYFUNCTION("IFERROR(TEXTJOIN("", "",TRUE,UNIQUE(FILTER(TRIM('Physician Portal Provider port'!B111:B117),'Physician Portal Provider port'!E111:E117=""New""))),"""")"),"Billing, Orders") | C27: New | D27: =IFERROR(__xludf.DUMMYFUNCTION("IFERROR(TEXTJOIN(CHAR(10),TRUE,FILTER(""• ""&TRIM('Physician Portal Provider port'!C111:C117),'Physician Portal Provider port'!E111:E117=""New"")),"""")"),"• Invoice Details • Pay Invoice & Raise Query • Order a Test • Order Details") | E27: Yes | F27: =SUMIFS('Physician Portal Provider port'!G111:G117,'Physician Portal Provider port'!E111:E117,"New") | G27: =SUMIFS('Physician Portal Provider port'!H111:H117,'Physician Portal Provider port'!E111:E117,"New")
A28: =TRIM('Physician Portal Provider port'!A118) | B28: =IFERROR(__xludf.DUMMYFUNCTION("IFERROR(TEXTJOIN("", "",TRUE,UNIQUE(FILTER(TRIM('Physician Portal Provider port'!B119:B125),'Physician Portal Provider port'!E119:E125=""New""))),"""")"),"Provider Account, Notifications, Security") | C28: New | D28: =IFERROR(__xludf.DUMMYFUNCTION("IFERROR(TEXTJOIN(CHAR(10),TRUE,FILTER(""• ""&TRIM('Physician Portal Provider port'!C119:C125),'Physician Portal Provider port'!E119:E125=""New"")),"""")"),"• Patient Flags • Notification preferences • Audit Log") | E28: Yes | F28: =SUMIFS('Physician Portal Provider port'!G119:G125,'Physician Portal Provider port'!E119:E125,"New") | G28: =SUMIFS('Physician Portal Provider port'!H119:H125,'Physician Portal Provider port'!E119:E125,"New")
A29: =TRIM('Physician Portal Provider port'!B126) | B29: =IFERROR(__xludf.DUMMYFUNCTION("IFERROR(TEXTJOIN("", "",TRUE,UNIQUE(FILTER(TRIM('Physician Portal Provider port'!B127:B131),'Physician Portal Provider port'!E127:E131=""New""))),"""")"),"Dashboard") | C29: New | D29: =IFERROR(__xludf.DUMMYFUNCTION("IFERROR(TEXTJOIN(CHAR(10),TRUE,FILTER(""• ""&TRIM('Physician Portal Provider port'!C127:C131),'Physician Portal Provider port'!E127:E131=""New"")),"""")"),"• Enrollment & activation • Engagement metrics • Outcome changes • Alert volume • Value & renewal metrics") | E29: Yes | F29: =SUMIFS('Physician Portal Provider port'!G127:G131,'Physician Portal Provider port'!E127:E131,"New") | G29: =SUMIFS('Physician Portal Provider port'!H127:H131,'Physician Portal Provider port'!E127:E131,"New")
A30: =TRIM('Physician Portal Provider port'!A132) | B30: =IFERROR(__xludf.DUMMYFUNCTION("IFERROR(TEXTJOIN("", "",TRUE,UNIQUE(FILTER(TRIM('Physician Portal Provider port'!B133:B140),'Physician Portal Provider port'!E133:E140=""New""))),"""")"),"Users, Providers, Provider, Non-clinical Users") | C30: New | D30: =IFERROR(__xludf.DUMMYFUNCTION("IFERROR(TEXTJOIN(CHAR(10),TRUE,FILTER(""• ""&TRIM('Physician Portal Provider port'!C133:C140),'Physician Portal Provider port'!E133:E140=""New"")),"""")"),"• Search, Filter • Bulk Add Providers • Add Provider • Provider Profile • Provider Bulk Import – CSV Import History • Edit Provider • Non-clinical Users List • Add User") | E30: Yes | F30: =SUMIFS('Physician Portal Provider port'!G133:G140,'Physician Portal Provider port'!E133:E140,"New") | G30: =SUMIFS('Physician Portal Provider port'!H133:H140,'Physician Portal Provider port'!E133:E140,"New")
A31: =TRIM('Physician Portal Provider port'!A141) | B31: =IFERROR(__xludf.DUMMYFUNCTION("IFERROR(TEXTJOIN("", "",TRUE,UNIQUE(FILTER(TRIM('Physician Portal Provider port'!B142:B146),'Physician Portal Provider port'!E142:E146=""New""))),"""")"),"Locations, Add Location, Location Details") | C31: New | D31: =IFERROR(__xludf.DUMMYFUNCTION("IFERROR(TEXTJOIN(CHAR(10),TRUE,FILTER(""• ""&TRIM('Physician Portal Provider port'!C142:C146),'Physician Portal Provider port'!E142:E146=""New"")),"""")"),"• Location List • Search, Filter • Add Location • Location Details • Edit Location") | E31: Yes | F31: =SUMIFS('Physician Portal Provider port'!G142:G146,'Physician Portal Provider port'!E142:E146,"New") | G31: =SUMIFS('Physician Portal Provider port'!H142:H146,'Physician Portal Provider port'!E142:E146,"New")
A32: =TRIM('Physician Portal Provider port'!A147) | B32: =IFERROR(__xludf.DUMMYFUNCTION("IFERROR(TEXTJOIN("", "",TRUE,UNIQUE(FILTER(TRIM('Physician Portal Provider port'!B148:B153),'Physician Portal Provider port'!E148:E153=""New""))),"""")"),"Provider Account, Employer Accounts, Patient Invitation, Notifications, Security") | C32: New | D32: =IFERROR(__xludf.DUMMYFUNCTION("IFERROR(TEXTJOIN(CHAR(10),TRUE,FILTER(""• ""&TRIM('Physician Portal Provider port'!C148:C153),'Physician Portal Provider port'!E148:E153=""New"")),"""")"),"• Patient Flags • Employer List & Add Employer • Invitation Channels • Invitation Reminders • Notification preferences • Audit Log") | E32: Yes | F32: =SUMIFS('Physician Portal Provider port'!G148:G153,'Physician Portal Provider port'!E148:E153,"New") | G32: =SUMIFS('Physician Portal Provider port'!H148:H153,'Physician Portal Provider port'!E148:E153,"New")
D33: Subtotal: Physician Portal: New Features | F33: =SUM(F20:F32) | G33: =SUM(G20:G32)
A35: Physician Portal: Modified Features (delta hours)
A36: =TRIM('Physician Portal Provider port'!A10) | B36: =IFERROR(__xludf.DUMMYFUNCTION("IFERROR(TEXTJOIN("", "",TRUE,UNIQUE(FILTER(TRIM('Physician Portal Provider port'!B11:B19),'Physician Portal Provider port'!E11:E19=""Modified""))),"""")"),"Dashboard") | C36: Modified | D36: =IFERROR(__xludf.DUMMYFUNCTION("IFERROR(TEXTJOIN(CHAR(10),TRUE,FILTER(""• ""&TRIM('Physician Portal Provider port'!C11:C19)&"": ""&TRIM('Physician Portal Provider port'!D11:D19),'Physician Portal Provider port'!E11:E19=""Modified"")),"""")"),"• Alert volume: As a Provider, I should see one list of items waiting on me and act on each one directly (review, open or reply).") | E36: Yes | F36: =SUMIFS('Physician Portal Provider port'!G11:G19,'Physician Portal Provider port'!E11:E19,"Modified")-2 | G36: =SUMIFS('Physician Portal Provider port'!H11:H19,'Physician Portal Provider port'!E11:E19,"Modified")-4
A37: =TRIM('Physician Portal Provider port'!A20) | B37: =IFERROR(__xludf.DUMMYFUNCTION("IFERROR(TEXTJOIN("", "",TRUE,UNIQUE(FILTER(TRIM('Physician Portal Provider port'!B21:B33),'Physician Portal Provider port'!E21:E33=""Modified""))),"""")"),"Patient") | C37: Modified | D37: =IFERROR(__xludf.DUMMYFUNCTION("IFERROR(TEXTJOIN(CHAR(10),TRUE,FILTER(""• ""&TRIM('Physician Portal Provider port'!C21:C33)&"": ""&TRIM('Physician Portal Provider port'!D21:D33),'Physician Portal Provider port'!E21:E33=""Modified"")),"""")"),"• Patient list: As a Provider, I should see my practice’s patients with risk level, ID, name, age and bio age, contact, location, primary provider, status, last interaction and last sync, and open a patient’s dashboard from the list.") | E37: Yes | F37: =SUMIFS('Physician Portal Provider port'!G21:G33,'Physician Portal Provider port'!E21:E33,"Modified")-4 | G37: =SUMIFS('Physician Portal Provider port'!H21:H33,'Physician Portal Provider port'!E21:E33,"Modified")-6
A38: =TRIM('Physician Portal Provider port'!A40) | B38: =IFERROR(__xludf.DUMMYFUNCTION("IFERROR(TEXTJOIN("", "",TRUE,UNIQUE(FILTER(TRIM('Physician Portal Provider port'!B41:B44),'Physician Portal Provider port'!E41:E44=""Modified""))),"""")"),"Scheduling") | C38: Modified | D38: =IFERROR(__xludf.DUMMYFUNCTION("IFERROR(TEXTJOIN(CHAR(10),TRUE,FILTER(""• ""&TRIM('Physician Portal Provider port'!C41:C44)&"": ""&TRIM('Physician Portal Provider port'!D41:D44),'Physician Portal Provider port'!E41:E44=""Modified"")),"""")"),"• Appointments view: As a physician, I can view appointments pulled from the EHR by day, week or month, as a calendar or a list, move between dates (Today, previous, next) and see the appointment count, with filters (type, status, in-person/virtual); view"&" only.") | E38: Yes | F38: =SUMIFS('Physician Portal Provider port'!G41:G44,'Physician Portal Provider port'!E41:E44,"Modified")-2 | G38: =SUMIFS('Physician Portal Provider port'!H41:H44,'Physician Portal Provider port'!E41:E44,"Modified")-2
A39: =TRIM('Physician Portal Provider port'!A71) | B39: =IFERROR(__xludf.DUMMYFUNCTION("IFERROR(TEXTJOIN("", "",TRUE,UNIQUE(FILTER(TRIM('Physician Portal Provider port'!B72:B103),'Physician Portal Provider port'!E72:E103=""Modified""))),"""")"),"AI Chart Summary, Patient Chart/ details") | C39: Modified | D39: =IFERROR(__xludf.DUMMYFUNCTION("IFERROR(TEXTJOIN(CHAR(10),TRUE,FILTER(""• ""&TRIM('Physician Portal Provider port'!C72:C103)&"": ""&TRIM('Physician Portal Provider port'!D72:D103),'Physician Portal Provider port'!E72:E103=""Modified"")),"""")"),"• Trends & flags: As a Provider, I should see the patient’s out-of-range results and trends to watch, each with its latest value and a mini trend. • sticky notes: As a Provider, I should see the patient’s sticky note count with the latest note, and be abl"&"e to add a note.") | E39: Yes | F39: =SUMIFS('Physician Portal Provider port'!G72:G103,'Physician Portal Provider port'!E72:E103,"Modified")-14 | G39: =SUMIFS('Physician Portal Provider port'!H72:H103,'Physician Portal Provider port'!E72:E103,"Modified")-14
A40: =TRIM('Physician Portal Provider port'!A110) | B40: =IFERROR(__xludf.DUMMYFUNCTION("IFERROR(TEXTJOIN("", "",TRUE,UNIQUE(FILTER(TRIM('Physician Portal Provider port'!B111:B117),'Physician Portal Provider port'!E111:E117=""Modified""))),"""")"),"Billing") | C40: Modified | D40: =IFERROR(__xludf.DUMMYFUNCTION("IFERROR(TEXTJOIN(CHAR(10),TRUE,FILTER(""• ""&TRIM('Physician Portal Provider port'!C111:C117)&"": ""&TRIM('Physician Portal Provider port'!D111:D117),'Physician Portal Provider port'!E111:E117=""Modified"")),"""")"),"• Practice Invoices: As a Clinic Manager, I can see my practice’s invoices for every month and download the statment and pay for it.") | E40: Yes | F40: =SUMIFS('Physician Portal Provider port'!G111:G117,'Physician Portal Provider port'!E111:E117,"Modified")-2 | G40: =SUMIFS('Physician Portal Provider port'!H111:H117,'Physician Portal Provider port'!E111:E117,"Modified")-2
D41: Subtotal: Physician Portal: Modified Features (delta hours) | F41: =SUM(F36:F40) | G41: =SUM(G36:G40)
A43: PATIENT APP
A44: Patient App: New Features
A45: =TRIM('Patient App'!A3) | B45: =IFERROR(__xludf.DUMMYFUNCTION("IFERROR(TEXTJOIN("", "",TRUE,UNIQUE(FILTER(TRIM('Patient App'!B4:B16),'Patient App'!E4:E16=""New""))),"""")"),"Patient Web – Onboarding & Consent, Patient Mobile – Onboarding & Consent, Patient Mobile – Onboarding") | C45: New | D45: =IFERROR(__xludf.DUMMYFUNCTION("IFERROR(TEXTJOIN(CHAR(10),TRUE,FILTER(""• ""&TRIM('Patient App'!C4:C16),'Patient App'!E4:E16=""New"")),"""")"),"• Invitation Email • Activate Account • Download App • First-Time Setup • Record Building & Ready") | E45: Yes | F45: =SUMIFS('Patient App'!G4:G16,'Patient App'!E4:E16,"New") | G45: =SUMIFS('Patient App'!H4:H16,'Patient App'!E4:E16,"New")
A46: =TRIM('Patient App'!A22) | B46: =IFERROR(__xludf.DUMMYFUNCTION("IFERROR(TEXTJOIN("", "",TRUE,UNIQUE(FILTER(TRIM('Patient App'!B23:B31),'Patient App'!E23:E31=""New""))),"""")"),"Data connections") | C46: New | D46: =IFERROR(__xludf.DUMMYFUNCTION("IFERROR(TEXTJOIN(CHAR(10),TRUE,FILTER(""• ""&TRIM('Patient App'!C23:C31),'Patient App'!E23:E31=""New"")),"""")"),"• Updates About Your Care • Record Building & Ready") | E46: Yes | F46: =SUMIFS('Patient App'!G23:G31,'Patient App'!E23:E31,"New") | G46: =SUMIFS('Patient App'!H23:H31,'Patient App'!E23:E31,"New")
A47: =TRIM('Patient App'!A32) | B47: =IFERROR(__xludf.DUMMYFUNCTION("IFERROR(TEXTJOIN("", "",TRUE,UNIQUE(FILTER(TRIM('Patient App'!B33:B43),'Patient App'!E33:E43=""New""))),"""")"),"Patient Mobile – Home, Patient Mobile – Member Home") | C47: New | D47: =IFERROR(__xludf.DUMMYFUNCTION("IFERROR(TEXTJOIN(CHAR(10),TRUE,FILTER(""• ""&TRIM('Patient App'!C33:C43),'Patient App'!E33:E43=""New"")),"""")"),"• Home Header • Bottom Navigation • Member App Tour • New Results • Cancelled Membership • Upcoming Appointments • Your Medicines • Notifications") | E47: Yes | F47: =SUMIFS('Patient App'!G33:G43,'Patient App'!E33:E43,"New") | G47: =SUMIFS('Patient App'!H33:H43,'Patient App'!E33:E43,"New")
A48: =TRIM('Patient App'!A44) | B48: =IFERROR(__xludf.DUMMYFUNCTION("IFERROR(TEXTJOIN("", "",TRUE,UNIQUE(FILTER(TRIM('Patient App'!B45:B53),'Patient App'!E45:E53=""New""))),"""")"),"Patient Mobile – Member Home, Patient Mobile – To Do, Patient Mobile – to do") | C48: New | D48: =IFERROR(__xludf.DUMMYFUNCTION("IFERROR(TEXTJOIN(CHAR(10),TRUE,FILTER(""• ""&TRIM('Patient App'!C45:C53),'Patient App'!E45:E53=""New"")),"""")"),"• Today’s To-do • Free To Do – Filters & Completed • Book a Test Through Inlay • Tests Scheduled and view • Pay & Place Order • Booking Confirmation • Member To Do – Today's To Do Overview • Member To Do – Upcoming & Booked • Member To Do – Filters & Comp"&"leted") | E48: Yes | F48: =SUMIFS('Patient App'!G45:G53,'Patient App'!E45:E53,"New") | G48: =SUMIFS('Patient App'!H45:H53,'Patient App'!E45:E53,"New")
A49: =TRIM('Patient App'!A54) | B49: =IFERROR(__xludf.DUMMYFUNCTION("IFERROR(TEXTJOIN("", "",TRUE,UNIQUE(FILTER(TRIM('Patient App'!B55:B66),'Patient App'!E55:E66=""New""))),"""")"),"Patient Mobile – Record") | C49: New | D49: =IFERROR(__xludf.DUMMYFUNCTION("IFERROR(TEXTJOIN(CHAR(10),TRUE,FILTER(""• ""&TRIM('Patient App'!C55:C66),'Patient App'!E55:E66=""New"")),"""")"),"• Biomarker Details • Record tabs Details • Record Sections • Medicines • Add to Record – Supplement • Add to Record – Allergy • Add to Record – Condition • Add to Record – Visit • Add to Record – Test Result") | E49: Yes | F49: =SUMIFS('Patient App'!G55:G66,'Patient App'!E55:E66,"New") | G49: =SUMIFS('Patient App'!H55:H66,'Patient App'!E55:E66,"New")
A50: =TRIM('Patient App'!A67) | B50: =IFERROR(__xludf.DUMMYFUNCTION("IFERROR(TEXTJOIN("", "",TRUE,UNIQUE(FILTER(TRIM('Patient App'!B68:B90),'Patient App'!E68:E90=""New""))),"""")"),"Patient Mobile – Plan") | C50: New | D50: =IFERROR(__xludf.DUMMYFUNCTION("IFERROR(TEXTJOIN(CHAR(10),TRUE,FILTER(""• ""&TRIM('Patient App'!C68:C90),'Patient App'!E68:E90=""New"")),"""")"),"• Plan Overview • Today – Exercise – Session & Logging • Today – Exercise – Easier Version or Own Programme • Today – Eat – Today’s Meals & Logging • Today – Eat – Diet Plan • Today – Eat – Drinks & History • Today – Mind – Today’s Practice • Today – Medi"&"cation • Today – Measure • Today – Sleep • History – Overview • History – Yesterday • History – Your History • History – Exercise & Eat • History – Sleep & Mind • History – Medication • Progress – Overview • Progress – Add Weight • Outlook – Projection") | E50: Yes | F50: =SUMIFS('Patient App'!G68:G90,'Patient App'!E68:E90,"New") | G50: =SUMIFS('Patient App'!H68:H90,'Patient App'!E68:E90,"New")
A51: =TRIM('Patient App'!A91) | B51: =IFERROR(__xludf.DUMMYFUNCTION("IFERROR(TEXTJOIN("", "",TRUE,UNIQUE(FILTER(TRIM('Patient App'!B92:B99),'Patient App'!E92:E99=""New""))),"""")"),"Patient Mobile – Upgrade") | C51: New | D51: =IFERROR(__xludf.DUMMYFUNCTION("IFERROR(TEXTJOIN(CHAR(10),TRUE,FILTER(""• ""&TRIM('Patient App'!C92:C99),'Patient App'!E92:E99=""New"")),"""")"),"• Start Your Plan • You’re Enrolled • Establish Your Baseline • Schedule Your Tests") | E51: Yes | F51: =SUMIFS('Patient App'!G92:G99,'Patient App'!E92:E99,"New") | G51: =SUMIFS('Patient App'!H92:H99,'Patient App'!E92:E99,"New")
A52: =TRIM('Patient App'!A100) | B52: =IFERROR(__xludf.DUMMYFUNCTION("IFERROR(TEXTJOIN("", "",TRUE,UNIQUE(FILTER(TRIM('Patient App'!B101:B104),'Patient App'!E101:E104=""New""))),"""")"),"Patient Mobile – Care") | C52: New | D52: =IFERROR(__xludf.DUMMYFUNCTION("IFERROR(TEXTJOIN(CHAR(10),TRUE,FILTER(""• ""&TRIM('Patient App'!C101:C104),'Patient App'!E101:E104=""New"")),"""")"),"• Care Tab • Category List • Item Details & Order • Book a Time") | E52: Yes | F52: =SUMIFS('Patient App'!G101:G104,'Patient App'!E101:E104,"New") | G52: =SUMIFS('Patient App'!H101:H104,'Patient App'!E101:E104,"New")
A53: =TRIM('Patient App'!A105) | B53: =IFERROR(__xludf.DUMMYFUNCTION("IFERROR(TEXTJOIN("", "",TRUE,UNIQUE(FILTER(TRIM('Patient App'!B106:B123),'Patient App'!E106:E123=""New""))),"""")"),"Patient Mobile – Ask Inlay") | C53: New | D53: =IFERROR(__xludf.DUMMYFUNCTION("IFERROR(TEXTJOIN(CHAR(10),TRUE,FILTER(""• ""&TRIM('Patient App'!C106:C123),'Patient App'!E106:E123=""New"")),"""")"),"• Ask a Question • Medical Disclaimer • Chat History • Chats by Category • Ask Inlay – Home • Ask Inlay – To Do • Ask Inlay – Record • Ask Inlay – Plan • Ask Inlay – Care • Ask Inlay – Chat Sessions • Ask Inlay – Response Guardrails") | E53: Yes | F53: =SUMIFS('Patient App'!G106:G123,'Patient App'!E106:E123,"New") | G53: =SUMIFS('Patient App'!H106:H123,'Patient App'!E106:E123,"New")
A54: =TRIM('Patient App'!A127) | B54: =IFERROR(__xludf.DUMMYFUNCTION("IFERROR(TEXTJOIN("", "",TRUE,UNIQUE(FILTER(TRIM('Patient App'!B128:B139),'Patient App'!E128:E139=""New""))),"""")"),"Patient Mobile – Upgrade, Billing, Patient Mobile – Ask Inlay") | C54: New | D54: =IFERROR(__xludf.DUMMYFUNCTION("IFERROR(TEXTJOIN(CHAR(10),TRUE,FILTER(""• ""&TRIM('Patient App'!C128:C139),'Patient App'!E128:E139=""New"")),"""")"),"• Choose Billing • Payment Method • Refunds • Credit Nearly Used") | E54: Yes | F54: =SUMIFS('Patient App'!G128:G139,'Patient App'!E128:E139,"New") | G54: =SUMIFS('Patient App'!H128:H139,'Patient App'!E128:E139,"New")
A55: =TRIM('Patient App'!A140) | B55: =IFERROR(__xludf.DUMMYFUNCTION("IFERROR(TEXTJOIN("", "",TRUE,UNIQUE(FILTER(TRIM('Patient App'!B141:B145),'Patient App'!E141:E145=""New""))),"""")"),"Setting, Patient Mobile – Profile") | C55: New | D55: =IFERROR(__xludf.DUMMYFUNCTION("IFERROR(TEXTJOIN(CHAR(10),TRUE,FILTER(""• ""&TRIM('Patient App'!C141:C145),'Patient App'!E141:E145=""New"")),"""")"),"• Change password • Your Doctor & Practice") | E55: Yes | F55: =SUMIFS('Patient App'!G141:G145,'Patient App'!E141:E145,"New") | G55: =SUMIFS('Patient App'!H141:H145,'Patient App'!E141:E145,"New")
D56: Subtotal: Patient App: New Features | F56: =SUM(F45:F55) | G56: =SUM(G45:G55)
A58: Patient App: Modified Features (delta hours)
A59: =TRIM('Patient App'!A127) | B59: =IFERROR(__xludf.DUMMYFUNCTION("IFERROR(TEXTJOIN("", "",TRUE,UNIQUE(FILTER(TRIM('Patient App'!B128:B139),'Patient App'!E128:E139=""Modified""))),"""")"),"Billing") | C59: Modified | D59: =IFERROR(__xludf.DUMMYFUNCTION("IFERROR(TEXTJOIN(CHAR(10),TRUE,FILTER(""• ""&TRIM('Patient App'!C128:C139)&"": ""&TRIM('Patient App'!D128:D139),'Patient App'!E128:E139=""Modified"")),"""")"),"• AI usage & overage: As a patient, I can see my AI chat usage against my allotment and, when it runs out, top it up by amount (e.g. $10 or $20), while the rest of the app keeps working.") | E59: Yes | F59: =SUMIFS('Patient App'!G128:G139,'Patient App'!E128:E139,"Modified")-8 | G59: =SUMIFS('Patient App'!H128:H139,'Patient App'!E128:E139,"Modified")-4
D60: Subtotal: Patient App: Modified Features (delta hours) | F60: =SUM(F59) | G60: =SUM(G59)
A62: COACH PORTAL
A63: Coach Portal: New Features
D64: No items
D65: Subtotal: Coach Portal: New Features | F65: =SUM(F64) | G65: =SUM(G64)
A67: Coach Portal: Modified Features (delta hours)
D68: No items
D69: Subtotal: Coach Portal: Modified Features (delta hours) | F69: =SUM(F68) | G69: =SUM(G68)
A71: SHARED BACKEND LAYERS
A72: Shared Backend Layers: New Features
D73: No items
D74: Subtotal: Shared Backend Layers: New Features | F74: =SUM(F73) | G74: =SUM(G73)
A76: Shared Backend Layers: Modified Features (delta hours)
D77: No items
D78: Subtotal: Shared Backend Layers: Modified Features (delta hours) | F78: =SUM(F77) | G78: =SUM(G77)
A80: SECTION B: REMOVED AND COVERED FEATURES (ALL PORTALS)
A81: Super Admin Portal: Removed / Covered
A82: =TRIM('Super Admin Portal Hol Portal'!A10) | B82: =IFERROR(__xludf.DUMMYFUNCTION("IFERROR(TEXTJOIN("", "",TRUE,UNIQUE(FILTER(TRIM('Super Admin Portal Hol Portal'!B11:B22),'Super Admin Portal Hol Portal'!E11:E22=""Removed""))),"""")"),"Dashboard") | C82: Removed | D82: =IFERROR(__xludf.DUMMYFUNCTION("IFERROR(TEXTJOIN(CHAR(10),TRUE,FILTER(""• ""&TRIM('Super Admin Portal Hol Portal'!C11:C22),'Super Admin Portal Hol Portal'!E11:E22=""Removed"")),"""")"),"• Care-gap view • Practice value & renewal") | E82: Yes | F82: =SUMIFS('Super Admin Portal Hol Portal'!G11:G22,'Super Admin Portal Hol Portal'!E11:E22,"Removed") | G82: =SUMIFS('Super Admin Portal Hol Portal'!H11:H22,'Super Admin Portal Hol Portal'!E11:E22,"Removed")
A83: =TRIM('Super Admin Portal Hol Portal'!A23) | B83: =IFERROR(__xludf.DUMMYFUNCTION("IFERROR(TEXTJOIN("", "",TRUE,UNIQUE(FILTER(TRIM('Super Admin Portal Hol Portal'!B24:B41),'Super Admin Portal Hol Portal'!E24:E41=""Removed""))),"""")"),"Protocols, Rules, Forecast, Eval, Evidence") | C83: Removed | D83: =IFERROR(__xludf.DUMMYFUNCTION("IFERROR(TEXTJOIN(CHAR(10),TRUE,FILTER(""• ""&TRIM('Super Admin Portal Hol Portal'!C24:C41),'Super Admin Portal Hol Portal'!E24:E41=""Removed"")),"""")"),"• Author protocols • Versioning • Approval workflow • Score weights • Forecast thresholds • Regression gate • Version log • Source expiry & re-review") | E83: Yes | F83: =SUMIFS('Super Admin Portal Hol Portal'!G24:G41,'Super Admin Portal Hol Portal'!E24:E41,"Removed") | G83: =SUMIFS('Super Admin Portal Hol Portal'!H24:H41,'Super Admin Portal Hol Portal'!E24:E41,"Removed")
A84: =TRIM('Super Admin Portal Hol Portal'!A42) | B84: =IFERROR(__xludf.DUMMYFUNCTION("IFERROR(TEXTJOIN("", "",TRUE,UNIQUE(FILTER(TRIM('Super Admin Portal Hol Portal'!B43:B54),'Super Admin Portal Hol Portal'!E43:E54=""Removed""))),"""")"),"Consent") | C84: Removed | D84: =IFERROR(__xludf.DUMMYFUNCTION("IFERROR(TEXTJOIN(CHAR(10),TRUE,FILTER(""• ""&TRIM('Super Admin Portal Hol Portal'!C43:C54),'Super Admin Portal Hol Portal'!E43:E54=""Removed"")),"""")"),"• Consent status") | E84: Yes | F84: =SUMIFS('Super Admin Portal Hol Portal'!G43:G54,'Super Admin Portal Hol Portal'!E43:E54,"Removed") | G84: =SUMIFS('Super Admin Portal Hol Portal'!H43:H54,'Super Admin Portal Hol Portal'!E43:E54,"Removed")
A85: =TRIM('Super Admin Portal Hol Portal'!A67) | B85: =IFERROR(__xludf.DUMMYFUNCTION("IFERROR(TEXTJOIN("", "",TRUE,UNIQUE(FILTER(TRIM('Super Admin Portal Hol Portal'!B68:B80),'Super Admin Portal Hol Portal'!E68:E80=""Removed""))),"""")"),"Billing") | C85: Removed | D85: =IFERROR(__xludf.DUMMYFUNCTION("IFERROR(TEXTJOIN(CHAR(10),TRUE,FILTER(""• ""&TRIM('Super Admin Portal Hol Portal'!C68:C80),'Super Admin Portal Hol Portal'!E68:E80=""Removed"")),"""")"),"• Seller-of-record config") | E85: Yes | F85: =SUMIFS('Super Admin Portal Hol Portal'!G68:G80,'Super Admin Portal Hol Portal'!E68:E80,"Removed") | G85: =SUMIFS('Super Admin Portal Hol Portal'!H68:H80,'Super Admin Portal Hol Portal'!E68:E80,"Removed")
D86: Subtotal: Super Admin Portal: Removed / Covered | F86: =SUM(F82:F85) | G86: =SUM(G82:G85)
A88: Physician Portal: Removed / Covered
A89: =TRIM('Physician Portal Provider port'!A10) | B89: =IFERROR(__xludf.DUMMYFUNCTION("IFERROR(TEXTJOIN("", "",TRUE,UNIQUE(FILTER(TRIM('Physician Portal Provider port'!B11:B19),'Physician Portal Provider port'!E11:E19=""Removed""))),"""")"),"Dashboard") | C89: Removed | D89: =IFERROR(__xludf.DUMMYFUNCTION("IFERROR(TEXTJOIN(CHAR(10),TRUE,FILTER(""• ""&TRIM('Physician Portal Provider port'!C11:C19),'Physician Portal Provider port'!E11:E19=""Removed"")),"""")"),"• Engagement metrics • Outcome changes • Physician review time • Value & renewal metrics") | E89: Yes | F89: =SUMIFS('Physician Portal Provider port'!G11:G19,'Physician Portal Provider port'!E11:E19,"Removed") | G89: =SUMIFS('Physician Portal Provider port'!H11:H19,'Physician Portal Provider port'!E11:E19,"Removed")
A90: =TRIM('Physician Portal Provider port'!A20) | B90: =IFERROR(__xludf.DUMMYFUNCTION("IFERROR(TEXTJOIN("", "",TRUE,UNIQUE(FILTER(TRIM('Physician Portal Provider port'!B21:B33),'Physician Portal Provider port'!E21:E33=""Removed""))),"""")"),"Patient") | C90: Removed | D90: =IFERROR(__xludf.DUMMYFUNCTION("IFERROR(TEXTJOIN(CHAR(10),TRUE,FILTER(""• ""&TRIM('Physician Portal Provider port'!C21:C33),'Physician Portal Provider port'!E21:E33=""Removed"")),"""")"),"• Patient’s HOL summary") | E90: Yes | F90: =SUMIFS('Physician Portal Provider port'!G21:G33,'Physician Portal Provider port'!E21:E33,"Removed") | G90: =SUMIFS('Physician Portal Provider port'!H21:H33,'Physician Portal Provider port'!E21:E33,"Removed")
A91: =TRIM('Physician Portal Provider port'!A55) | B91: =IFERROR(__xludf.DUMMYFUNCTION("IFERROR(TEXTJOIN("", "",TRUE,UNIQUE(FILTER(TRIM('Physician Portal Provider port'!B56:B59),'Physician Portal Provider port'!E56:E59=""Removed""))),"""")"),"Report review") | C91: Removed | D91: =IFERROR(__xludf.DUMMYFUNCTION("IFERROR(TEXTJOIN(CHAR(10),TRUE,FILTER(""• ""&TRIM('Physician Portal Provider port'!C56:C59),'Physician Portal Provider port'!E56:E59=""Removed"")),"""")"),"• Review AI report • Approve / edit / reject • Release to patient • Batch & review time") | E91: Yes | F91: =SUMIFS('Physician Portal Provider port'!G56:G59,'Physician Portal Provider port'!E56:E59,"Removed") | G91: =SUMIFS('Physician Portal Provider port'!H56:H59,'Physician Portal Provider port'!E56:E59,"Removed")
A92: =TRIM('Physician Portal Provider port'!A104) | B92: =IFERROR(__xludf.DUMMYFUNCTION("IFERROR(TEXTJOIN("", "",TRUE,UNIQUE(FILTER(TRIM('Physician Portal Provider port'!B105:B106),'Physician Portal Provider port'!E105:E106=""Removed""))),"""")"),"Plan builder") | C92: Removed | D92: =IFERROR(__xludf.DUMMYFUNCTION("IFERROR(TEXTJOIN(CHAR(10),TRUE,FILTER(""• ""&TRIM('Physician Portal Provider port'!C105:C106),'Physician Portal Provider port'!E105:E106=""Removed"")),"""")"),"• Goals & interventions • Approve goals") | E92: Yes | F92: =SUMIFS('Physician Portal Provider port'!G105:G106,'Physician Portal Provider port'!E105:E106,"Removed") | G92: =SUMIFS('Physician Portal Provider port'!H105:H106,'Physician Portal Provider port'!E105:E106,"Removed")
A93: =TRIM('Physician Portal Provider port'!A107) | B93: =IFERROR(__xludf.DUMMYFUNCTION("IFERROR(TEXTJOIN("", "",TRUE,UNIQUE(FILTER(TRIM('Physician Portal Provider port'!B108:B109),'Physician Portal Provider port'!E108:E109=""Removed""))),"""")"),"Alerts") | C93: Removed | D93: =IFERROR(__xludf.DUMMYFUNCTION("IFERROR(TEXTJOIN(CHAR(10),TRUE,FILTER(""• ""&TRIM('Physician Portal Provider port'!C108:C109),'Physician Portal Provider port'!E108:E109=""Removed"")),"""")"),"• Acknowledge & route") | E93: Yes | F93: =SUMIFS('Physician Portal Provider port'!G108:G109,'Physician Portal Provider port'!E108:E109,"Removed") | G93: =SUMIFS('Physician Portal Provider port'!H108:H109,'Physician Portal Provider port'!E108:E109,"Removed")
A94: =TRIM('Physician Portal Provider port'!A110) | B94: =IFERROR(__xludf.DUMMYFUNCTION("IFERROR(TEXTJOIN("", "",TRUE,UNIQUE(FILTER(TRIM('Physician Portal Provider port'!B111:B117),'Physician Portal Provider port'!E111:E117=""Removed""))),"""")"),"Billing") | C94: Removed | D94: =IFERROR(__xludf.DUMMYFUNCTION("IFERROR(TEXTJOIN(CHAR(10),TRUE,FILTER(""• ""&TRIM('Physician Portal Provider port'!C111:C117),'Physician Portal Provider port'!E111:E117=""Removed"")),"""")"),"• Revenue-share statements • Physician review fee") | E94: Yes | F94: =SUMIFS('Physician Portal Provider port'!G111:G117,'Physician Portal Provider port'!E111:E117,"Removed") | G94: =SUMIFS('Physician Portal Provider port'!H111:H117,'Physician Portal Provider port'!E111:E117,"Removed")
A95: =TRIM('Physician Portal Provider port'!A118) | B95: =IFERROR(__xludf.DUMMYFUNCTION("IFERROR(TEXTJOIN("", "",TRUE,UNIQUE(FILTER(TRIM('Physician Portal Provider port'!B119:B125),'Physician Portal Provider port'!E119:E125=""Removed""))),"""")"),"Billing") | C95: Removed | D95: =IFERROR(__xludf.DUMMYFUNCTION("IFERROR(TEXTJOIN(CHAR(10),TRUE,FILTER(""• ""&TRIM('Physician Portal Provider port'!C119:C125),'Physician Portal Provider port'!E119:E125=""Removed"")),"""")"),"• Entitlements") | E95: Yes | F95: =SUMIFS('Physician Portal Provider port'!G119:G125,'Physician Portal Provider port'!E119:E125,"Removed") | G95: =SUMIFS('Physician Portal Provider port'!H119:H125,'Physician Portal Provider port'!E119:E125,"Removed")
D96: Subtotal: Physician Portal: Removed / Covered | F96: =SUM(F89:F95) | G96: =SUM(G89:G95)
A98: Patient App: Removed / Covered
A99: =TRIM('Patient App'!A17) | B99: =IFERROR(__xludf.DUMMYFUNCTION("IFERROR(TEXTJOIN("", "",TRUE,UNIQUE(FILTER(TRIM('Patient App'!B18:B21),'Patient App'!E18:E21=""Removed""))),"""")"),"Intake & goals") | C99: Removed | D99: =IFERROR(__xludf.DUMMYFUNCTION("IFERROR(TEXTJOIN(CHAR(10),TRUE,FILTER(""• ""&TRIM('Patient App'!C18:C21),'Patient App'!E18:E21=""Removed"")),"""")"),"• AI-guided intake • Save & resume • Select goals") | E99: Yes | F99: =SUMIFS('Patient App'!G18:G21,'Patient App'!E18:E21,"Removed") | G99: =SUMIFS('Patient App'!H18:H21,'Patient App'!E18:E21,"Removed")
A100: =TRIM('Patient App'!A22) | B100: =IFERROR(__xludf.DUMMYFUNCTION("IFERROR(TEXTJOIN("", "",TRUE,UNIQUE(FILTER(TRIM('Patient App'!B23:B31),'Patient App'!E23:E31=""Removed""))),"""")"),"Data connections") | C100: Removed | D100: =IFERROR(__xludf.DUMMYFUNCTION("IFERROR(TEXTJOIN(CHAR(10),TRUE,FILTER(""• ""&TRIM('Patient App'!C23:C31),'Patient App'!E23:E31=""Removed"")),"""")"),"• Authorize EMR • Multi-hospital auth • Revoke access • Upload report • Extraction preview") | E100: Yes | F100: =SUMIFS('Patient App'!G23:G31,'Patient App'!E23:E31,"Removed") | G100: =SUMIFS('Patient App'!H23:H31,'Patient App'!E23:E31,"Removed")
A101: =TRIM('Patient App'!A54) | B101: =IFERROR(__xludf.DUMMYFUNCTION("IFERROR(TEXTJOIN("", "",TRUE,UNIQUE(FILTER(TRIM('Patient App'!B55:B66),'Patient App'!E55:E66=""Removed""))),"""")"),"Health record") | C101: Removed | D101: =IFERROR(__xludf.DUMMYFUNCTION("IFERROR(TEXTJOIN(CHAR(10),TRUE,FILTER(""• ""&TRIM('Patient App'!C55:C66),'Patient App'!E55:E66=""Removed"")),"""")"),"• Gauge view & filters") | E101: Yes | F101: =SUMIFS('Patient App'!G55:G66,'Patient App'!E55:E66,"Removed") | G101: =SUMIFS('Patient App'!H55:H66,'Patient App'!E55:E66,"Removed")
A102: =TRIM('Patient App'!A67) | B102: =IFERROR(__xludf.DUMMYFUNCTION("IFERROR(TEXTJOIN("", "",TRUE,UNIQUE(FILTER(TRIM('Patient App'!B68:B90),'Patient App'!E68:E90=""Removed""))),"""")"),"Plan & tasks") | C102: Removed | D102: =IFERROR(__xludf.DUMMYFUNCTION("IFERROR(TEXTJOIN(CHAR(10),TRUE,FILTER(""• ""&TRIM('Patient App'!C68:C90),'Patient App'!E68:E90=""Removed"")),"""")"),"• Daily/weekly actions • Check-ins • Adherence logging • Mindfulness & stress") | E102: Yes | F102: =SUMIFS('Patient App'!G68:G90,'Patient App'!E68:E90,"Removed") | G102: =SUMIFS('Patient App'!H68:H90,'Patient App'!E68:E90,"Removed")
A103: =TRIM('Patient App'!A105) | B103: =IFERROR(__xludf.DUMMYFUNCTION("IFERROR(TEXTJOIN("", "",TRUE,UNIQUE(FILTER(TRIM('Patient App'!B106:B123),'Patient App'!E106:E123=""Removed""))),"""")"),"Chat, Why HOL said this") | C103: Removed | D103: =IFERROR(__xludf.DUMMYFUNCTION("IFERROR(TEXTJOIN(CHAR(10),TRUE,FILTER(""• ""&TRIM('Patient App'!C106:C123),'Patient App'!E106:E123=""Removed"")),"""")"),"• Safety template • Refuse & route clinical • Emergency redirect • Answer traceability view • Monitoring-limits disclosure") | E103: Yes | F103: =SUMIFS('Patient App'!G106:G123,'Patient App'!E106:E123,"Removed") | G103: =SUMIFS('Patient App'!H106:H123,'Patient App'!E106:E123,"Removed")
A104: =TRIM('Patient App'!A124) | B104: =IFERROR(__xludf.DUMMYFUNCTION("IFERROR(TEXTJOIN("", "",TRUE,UNIQUE(FILTER(TRIM('Patient App'!B125:B126),'Patient App'!E125:E126=""Removed""))),"""")"),"Messages") | C104: Removed | D104: =IFERROR(__xludf.DUMMYFUNCTION("IFERROR(TEXTJOIN(CHAR(10),TRUE,FILTER(""• ""&TRIM('Patient App'!C125:C126),'Patient App'!E125:E126=""Removed"")),"""")"),"• Message care team • Book & message coach") | E104: Yes | F104: =SUMIFS('Patient App'!G125:G126,'Patient App'!E125:E126,"Removed") | G104: =SUMIFS('Patient App'!H125:H126,'Patient App'!E125:E126,"Removed")
A105: =TRIM('Patient App'!A127) | B105: =IFERROR(__xludf.DUMMYFUNCTION("IFERROR(TEXTJOIN("", "",TRUE,UNIQUE(FILTER(TRIM('Patient App'!B128:B139),'Patient App'!E128:E139=""Removed""))),"""")"),"Billing") | C105: Removed | D105: =IFERROR(__xludf.DUMMYFUNCTION("IFERROR(TEXTJOIN(CHAR(10),TRUE,FILTER(""• ""&TRIM('Patient App'!C128:C139),'Patient App'!E128:E139=""Removed"")),"""")"),"• Payment methods • Pay & BNPL") | E105: Yes | F105: =SUMIFS('Patient App'!G128:G139,'Patient App'!E128:E139,"Removed") | G105: =SUMIFS('Patient App'!H128:H139,'Patient App'!E128:E139,"Removed")
A106: =TRIM('Patient App'!A146) | B106: =IFERROR(__xludf.DUMMYFUNCTION("IFERROR(TEXTJOIN("", "",TRUE,UNIQUE(FILTER(TRIM('Patient App'!B147:B151),'Patient App'!E147:E151=""Removed""))),"""")"),"Reports") | C106: Removed | D106: =IFERROR(__xludf.DUMMYFUNCTION("IFERROR(TEXTJOIN(CHAR(10),TRUE,FILTER(""• ""&TRIM('Patient App'!C147:C151),'Patient App'!E147:E151=""Removed"")),"""")"),"• View approved report • L / M split & provenance • Quarter-over-quarter • View monthly summary • Progress survey") | E106: Yes | F106: =SUMIFS('Patient App'!G147:G151,'Patient App'!E147:E151,"Removed") | G106: =SUMIFS('Patient App'!H147:H151,'Patient App'!E147:E151,"Removed")
D107: Subtotal: Patient App: Removed / Covered | F107: =SUM(F99:F106) | G107: =SUM(G99:G106)
A109: Coach Portal: Removed / Covered
A110: =TRIM('Coach Portal'!A3) | B110: =IFERROR(__xludf.DUMMYFUNCTION("IFERROR(TEXTJOIN("", "",TRUE,UNIQUE(FILTER(TRIM('Coach Portal'!B4:B5),'Coach Portal'!G4:G5=""Removed""))),"""")"),"Auth") | C110: Removed | D110: =IFERROR(__xludf.DUMMYFUNCTION("IFERROR(TEXTJOIN(CHAR(10),TRUE,FILTER(""• ""&TRIM('Coach Portal'!C4:C5),'Coach Portal'!G4:G5=""Removed"")),"""")"),"• Login & MFA • Scoped access (RBAC)") | E110: Yes | F110: =SUMIFS('Coach Portal'!H4:H5,'Coach Portal'!G4:G5,"Removed") | G110: =SUMIFS('Coach Portal'!I4:I5,'Coach Portal'!G4:G5,"Removed")
A111: =TRIM('Coach Portal'!A6) | B111: =IFERROR(__xludf.DUMMYFUNCTION("IFERROR(TEXTJOIN("", "",TRUE,UNIQUE(FILTER(TRIM('Coach Portal'!B7:B10),'Coach Portal'!G7:G10=""Removed""))),"""")"),"Context") | C111: Removed | D111: =IFERROR(__xludf.DUMMYFUNCTION("IFERROR(TEXTJOIN(CHAR(10),TRUE,FILTER(""• ""&TRIM('Coach Portal'!C7:C10),'Coach Portal'!G7:G10=""Removed"")),"""")"),"• Assigned patient list • Physician-approved goals • Lifestyle plan • Adherence view") | E111: Yes | F111: =SUMIFS('Coach Portal'!H7:H10,'Coach Portal'!G7:G10,"Removed") | G111: =SUMIFS('Coach Portal'!I7:I10,'Coach Portal'!G7:G10,"Removed")
A112: =TRIM('Coach Portal'!A11) | B112: =IFERROR(__xludf.DUMMYFUNCTION("IFERROR(TEXTJOIN("", "",TRUE,UNIQUE(FILTER(TRIM('Coach Portal'!B12:B13),'Coach Portal'!G12:G13=""Removed""))),"""")"),"Scheduling") | C112: Removed | D112: =IFERROR(__xludf.DUMMYFUNCTION("IFERROR(TEXTJOIN(CHAR(10),TRUE,FILTER(""• ""&TRIM('Coach Portal'!C12:C13),'Coach Portal'!G12:G13=""Removed"")),"""")"),"• View & manage sessions • Availability") | E112: Yes | F112: =SUMIFS('Coach Portal'!H12:H13,'Coach Portal'!G12:G13,"Removed") | G112: =SUMIFS('Coach Portal'!I12:I13,'Coach Portal'!G12:G13,"Removed")
A113: =TRIM('Coach Portal'!A14) | B113: =IFERROR(__xludf.DUMMYFUNCTION("IFERROR(TEXTJOIN("", "",TRUE,UNIQUE(FILTER(TRIM('Coach Portal'!B15:B16),'Coach Portal'!G15:G16=""Removed""))),"""")"),"Messaging") | C113: Removed | D113: =IFERROR(__xludf.DUMMYFUNCTION("IFERROR(TEXTJOIN(CHAR(10),TRUE,FILTER(""• ""&TRIM('Coach Portal'!C15:C16),'Coach Portal'!G15:G16=""Removed"")),"""")"),"• Secure patient messaging • Wellness boundary") | E113: Yes | F113: =SUMIFS('Coach Portal'!H15:H16,'Coach Portal'!G15:G16,"Removed") | G113: =SUMIFS('Coach Portal'!I15:I16,'Coach Portal'!G15:G16,"Removed")
...

Sheet Portal Deviation
A1: Portal deviation: 18 Sep 2026 scope vs 30 Oct 2026 scope (hours = FE + BE)
A3: Portal | B3: Retained hrs | C3: Modified hrs (18 Sep) | D3: Removed hrs | E3: Covered hrs | F3: Original scope hrs (18 Sep) | G3: New hrs added (+) | H3: Modified change hrs (+/-) | I3: Removed + Covered hrs (-) | J3: Net change hrs | K3: Current scope hrs (30 Oct) | L3: % added (New / Original) | M3: % removed ((Removed + Covered) / Original) | N3: Net deviation %
A4: Super Admin Portal | B4: =SUMIFS('Super Admin Portal Hol Portal'!G3:G84,'Super Admin Portal Hol Portal'!E3:E84,"Retained")+SUMIFS('Super Admin Portal Hol Portal'!H3:H84,'Super Admin Portal Hol Portal'!E3:E84,"Retained") | C4: 38 | D4: =SUMIFS('Super Admin Portal Hol Portal'!G3:G84,'Super Admin Portal Hol Portal'!E3:E84,"Removed")+SUMIFS('Super Admin Portal Hol Portal'!H3:H84,'Super Admin Portal Hol Portal'!E3:E84,"Removed") | E4: =SUMIFS('Super Admin Portal Hol Portal'!G3:G84,'Super Admin Portal Hol Portal'!E3:E84,"Covered")+SUMIFS('Super Admin Portal Hol Portal'!H3:H84,'Super Admin Portal Hol Portal'!E3:E84,"Covered") | F4: =B4+C4+D4+E4 | G4: =SUMIFS('Super Admin Portal Hol Portal'!G3:G84,'Super Admin Portal Hol Portal'!E3:E84,"New")+SUMIFS('Super Admin Portal Hol Portal'!H3:H84,'Super Admin Portal Hol Portal'!E3:E84,"New") | H4: =SUMIFS('Super Admin Portal Hol Portal'!G3:G84,'Super Admin Portal Hol Portal'!E3:E84,"Modified")+SUMIFS('Super Admin Portal Hol Portal'!H3:H84,'Super Admin Portal Hol Portal'!E3:E84,"Modified")-C4 | I4: =D4+E4 | J4: =G4+H4-I4 | K4: =F4+J4 | L4: =IF(F4=0,0,G4/F4) | M4: =IF(F4=0,0,I4/F4) | N4: =IF(F4=0,0,J4/F4)
A5: Physician Portal | B5: =SUMIFS('Physician Portal Provider port'!G3:G153,'Physician Portal Provider port'!E3:E153,"Retained")+SUMIFS('Physician Portal Provider port'!H3:H153,'Physician Portal Provider port'!E3:E153,"Retained") | C5: 52 | D5: =SUMIFS('Physician Portal Provider port'!G3:G153,'Physician Portal Provider port'!E3:E153,"Removed")+SUMIFS('Physician Portal Provider port'!H3:H153,'Physician Portal Provider port'!E3:E153,"Removed") | E5: =SUMIFS('Physician Portal Provider port'!G3:G153,'Physician Portal Provider port'!E3:E153,"Covered")+SUMIFS('Physician Portal Provider port'!H3:H153,'Physician Portal Provider port'!E3:E153,"Covered") | F5: =B5+C5+D5+E5 | G5: =SUMIFS('Physician Portal Provider port'!G3:G153,'Physician Portal Provider port'!E3:E153,"New")+SUMIFS('Physician Portal Provider port'!H3:H153,'Physician Portal Provider port'!E3:E153,"New") | H5: =SUMIFS('Physician Portal Provider port'!G3:G153,'Physician Portal Provider port'!E3:E153,"Modified")+SUMIFS('Physician Portal Provider port'!H3:H153,'Physician Portal Provider port'!E3:E153,"Modified")-C5 | I5: =D5+E5 | J5: =G5+H5-I5 | K5: =F5+J5 | L5: =IF(F5=0,0,G5/F5) | M5: =IF(F5=0,0,I5/F5) | N5: =IF(F5=0,0,J5/F5)
A6: Patient App | B6: =SUMIFS('Patient App'!G3:G151,'Patient App'!E3:E151,"Retained")+SUMIFS('Patient App'!H3:H151,'Patient App'!E3:E151,"Retained") | C6: 12 | D6: =SUMIFS('Patient App'!G3:G151,'Patient App'!E3:E151,"Removed")+SUMIFS('Patient App'!H3:H151,'Patient App'!E3:E151,"Removed") | E6: =SUMIFS('Patient App'!G3:G151,'Patient App'!E3:E151,"Covered")+SUMIFS('Patient App'!H3:H151,'Patient App'!E3:E151,"Covered") | F6: =B6+C6+D6+E6 | G6: =SUMIFS('Patient App'!G3:G151,'Patient App'!E3:E151,"New")+SUMIFS('Patient App'!H3:H151,'Patient App'!E3:E151,"New") | H6: =SUMIFS('Patient App'!G3:G151,'Patient App'!E3:E151,"Modified")+SUMIFS('Patient App'!H3:H151,'Patient App'!E3:E151,"Modified")-C6 | I6: =D6+E6 | J6: =G6+H6-I6 | K6: =F6+J6 | L6: =IF(F6=0,0,G6/F6) | M6: =IF(F6=0,0,I6/F6) | N6: =IF(F6=0,0,J6/F6)
A7: Coach Portal | B7: =SUMIFS('Coach Portal'!H3:H21,'Coach Portal'!G3:G21,"Retained")+SUMIFS('Coach Portal'!I3:I21,'Coach Portal'!G3:G21,"Retained") | C7: 0 | D7: =SUMIFS('Coach Portal'!H3:H21,'Coach Portal'!G3:G21,"Removed")+SUMIFS('Coach Portal'!I3:I21,'Coach Portal'!G3:G21,"Removed") | E7: =SUMIFS('Coach Portal'!H3:H21,'Coach Portal'!G3:G21,"Covered")+SUMIFS('Coach Portal'!I3:I21,'Coach Portal'!G3:G21,"Covered") | F7: =B7+C7+D7+E7 | G7: =SUMIFS('Coach Portal'!H3:H21,'Coach Portal'!G3:G21,"New")+SUMIFS('Coach Portal'!I3:I21,'Coach Portal'!G3:G21,"New") | H7: =SUMIFS('Coach Portal'!H3:H21,'Coach Portal'!G3:G21,"Modified")+SUMIFS('Coach Portal'!I3:I21,'Coach Portal'!G3:G21,"Modified")-C7 | I7: =D7+E7 | J7: =G7+H7-I7 | K7: =F7+J7 | L7: =IF(F7=0,0,G7/F7) | M7: =IF(F7=0,0,I7/F7) | N7: 0
A8: Shared Backend Layers | B8: =SUMIFS('Shared Backend Layers'!H3:H101,'Shared Backend Layers'!G3:G101,"Retained")+SUMIFS('Shared Backend Layers'!I3:I101,'Shared Backend Layers'!G3:G101,"Retained") | C8: 0 | D8: =SUMIFS('Shared Backend Layers'!H3:H101,'Shared Backend Layers'!G3:G101,"Removed")+SUMIFS('Shared Backend Layers'!I3:I101,'Shared Backend Layers'!G3:G101,"Removed") | E8: =SUMIFS('Shared Backend Layers'!H3:H101,'Shared Backend Layers'!G3:G101,"Covered")+SUMIFS('Shared Backend Layers'!I3:I101,'Shared Backend Layers'!G3:G101,"Covered") | F8: =B8+C8+D8+E8 | G8: =SUMIFS('Shared Backend Layers'!H3:H101,'Shared Backend Layers'!G3:G101,"New")+SUMIFS('Shared Backend Layers'!I3:I101,'Shared Backend Layers'!G3:G101,"New") | H8: =SUMIFS('Shared Backend Layers'!H3:H101,'Shared Backend Layers'!G3:G101,"Modified")+SUMIFS('Shared Backend Layers'!I3:I101,'Shared Backend Layers'!G3:G101,"Modified")-C8 | I8: =D8+E8 | J8: =G8+H8-I8 | K8: =F8+J8 | L8: =IF(F8=0,0,G8/F8) | M8: =IF(F8=0,0,I8/F8) | N8: 0
A9: Total (all portals) | B9: =SUM(B4:B8) | C9: =SUM(C4:C8) | D9: =SUM(D4:D8) | E9: =SUM(E4:E8) | F9: =SUM(F4:F8) | G9: =SUM(G4:G8) | H9: =SUM(H4:H8) | I9: =SUM(I4:I8) | ... K9: =SUM(K4:K8) | L9: =IF(F9=0,0,G9/F9) | M9: =IF(F9=0,0,I9/F9) | N9: =IF(F9=0,0,J9/F9)

Sheet Super Admin Portal  Hol Portal
G1: =SUM(G3:G84) | H1: =SUM(H3:H84)
A2: SR.NO | B2: MODULE | C2: CAPABILITY | D2: USER STORY | E2: STATUS | F2: REQUIRED | G2: FRONT END | H2: BACK END | I2: DESIGN LINK | J2: COMMENT
A3: Login
B4: Invitation | C4: Invitation Email | D4: As a Super Admin, I should receive an invitation email from the platform admin who invited me, with my role, my email, a one-time activation code and an “Activate account” button, so that I can activate my account. | E4: Retained | F4: Yes | G4: 2 | H4: 2 | I4: Prototype Link
B5: Activate Account | C5: Activate Account & Set Password | D5: As a Super Admin, I should be able to activate my account with the code from my email and create my password. | E5: Retained | F5: Yes | G5: 2 | H5: 2 | I5: Prototype Link
B6: Activate Account | C6: Two-Factor Setup | D6: As a Super Admin, I should be able to set up two-factor authentication with an authenticator app so that my account is protected. | E6: Retained | F6: Yes | G6: 2 | H6: 2 | I6: Prototype Link
B7: Sign In | C7: Sign In | D7: As a Super Admin, I should be able to sign in to the admin console with my Organization ID, email and password, with an option to remember me on the same device. | E7: Retained | F7: Yes | G7: 2 | H7: 2 | I7: Prototype Link
B8: Sign In | C8: Two-Factor Verification | D8: As a Super Admin, I should enter a code from my authenticator app to complete sign-in when asked (once a week and on a new device). | E8: Retained | F8: Yes | G8: 2 | H8: 2 | I8: Prototype Link
B9: Forgot Password | C9: Forgot & Reset Password | D9: As a Super Admin, I want to reset my password with a code sent to my email so that I can get back into my account if I forget it. | E9: Retained | F9: Yes | G9: 2 | H9: 2 | I9: Prototype Link
A10: DASHBOARDS
B11: Dashboard | C11: Engagement & outcomes | D11: As a HOL analyst, I can view cohort, engagement and outcome dashboards. | E11: Retained | F11: Yes | G11: 4 | H11: 6 | I11: Prototype Link
B12: Dashboard | C12: Care-gap view | D12: As a HOL analyst, I can view care gaps across a panel. | E12: Removed | F12: Yes | G12: 2 | H12: 4
B13: Dashboard | C13: Practice value & renewal | D13: As a HOL analyst, I can view value and renewal-supporting metrics. | E13: Removed | F13: Yes | G13: 4 | H13: 6
B14: Navigation | C14: Navigation & Notifications | D14: As a Super Admin, I should be able to move between Dashboard, Practices and Settings from a collapsible side menu, and view my notifications from the bell icon. | E14: New | F14: Yes | G14: 2 | H14: 2 | I14: Prototype Link
B15: Navigation | C15: Global Search | D15: As a Super Admin, I should be able to search across the admin console from the top bar. | E15: New | F15: Yes | G15: 2 | H15: 4 | I15: Prototype Link
B16: Dashboard | C16: Dashboard Filters | D16: As a Super Admin, I should be able to filter the dashboard by date range (preset or custom) and by all regions or one region. | E16: New | F16: Yes | G16: 2 | H16: 2 | I16: Prototype Link
B17: Dashboard | C17: Summary Cards | D17: As a Super Admin, I should see the number of users onboarded, providers onboarded and patients enrolled, each against its total with the percentage. | E17: New | F17: Yes | G17: 2 | H17: 2 | I17: Prototype Link
B18: Dashboard | C18: Enrolment by State | D18: As a Super Admin, I should see enrolment across the US on a map by state status, with an enrolment summary and the three highest and three lowest regions. | E18: New | F18: Yes | G18: 4 | H18: 2 | I18: Prototype Link
B19: Dashboard | C19: Invites & Conversion | D19: As a Super Admin, I should see invites sent, patients enrolled and the conversion rate, with a weekly chart of invites against enrolments. | E19: New | F19: Yes | G19: 2 | H19: 2 | I19: Prototype Link
B20: Dashboard | C20: Patient Status & Enrolment Funnel | D20: As a Super Admin, I should see how many patients are enrolled, pending or declined, and the enrolment funnel from invited to answered to enrolled. | E20: New | F20: Yes | G20: 2 | H20: 2 | I20: Prototype Link
B21: Dashboard | C21: Practices on Inlay | D21: As a Super Admin, I should see the total number of practices, how many were added in the selected period, and a chart of practices added over time. | E21: New | F21: Yes | G21: 2 | H21: 2 | I21: Prototype Link
B22: Dashboard | C22: Region Table | D22: As a Super Admin, I should view each region’s practices, providers, patients, enrolment counts and enrolment rate, listed from lowest to highest rate. | E22: New | F22: Yes | G22: 4 | H22: 2 | I22: Prototype Link
A23: CLINICAL CONTENT CONSOLE
B24: Clinical Content | C24: Clinical Content Overview | D24: As a super admin, I should see all clinical content areas (catalog, protocols, rules, forecast, eval and evidence) in one place and open any of them. | E24: New | G24: 2 | H24: 2 | I24: Prototype Link
B25: Catalog | C25: Biomarker definitions | D25: As a clinical admin, I can maintain biomarker definitions and canonical units by adding, editing, search, filter and retiring biomarkers. | E25: Modified | F25: Yes | G25: 4 | H25: 6 | I25: Prototype Link
B26: Catalog | C26: Range management | D26: As a clinical admin, I can set lab range, physician target, and HOL optimal range separately. | E26: Retained | F26: Yes | G26: 4 | H26: 6 | I26: Prototype Link
B27: Catalog | C27: Range List | D27: As a clinical admin, I should see each biomarker’s unit, lab range, physician target and Inlay optimal range in one list, and search, filter, select and export it. | E27: New | G27: 2 | H27: 2 | I27: Prototype Link
B28: Catalog | C28: Sex/age rules | D28: As a clinical admin, I can set sex/age display and scoring rules by adding, editing and deleting them. | E28: Retained | F28: Yes | G28: 2 | H28: 4 | I28: Prototype Link
B29: Catalog | C29: Sex/Age Rule List | D29: As a clinical admin, I should see all sex and age rules with the biomarker, sex, age, ranges, display and scoring for each, and search, filter them. | E29: New | G29: 2 | H29: 2 | I29: Prototype Link
B30: Protocols | C30: Author protocols | D30: As the Medical Director, I can author protocols and SOPs. | E30: Removed | F30: Yes | G30: 4 | H30: 6
B31: Protocols | C31: Versioning | D31: As the Medical Director, I can version the library with source citations. | E31: Removed | F31: Yes | G31: 4 | H31: 6
B32: Protocols | C32: Approval workflow | D32: As the Medical Director, I can approve content before it goes live. | E32: Removed | F32: Yes | G32: 2 | H32: 4
B33: Rules | C33: Alert rules | D33: As a clinical admin, I can configure the deterministic safety/priority rules by adding and editing rules and turning each one on or off. | E33: Modified | F33: Yes | G33: 4 | H33: 6 | I33: Prototype Link
B34: Rules | C34: Alert Rule List | D34: As a clinical admin, I should see all alert rules with their condition, priority, action and whether each is on, and search, filter. | E34: New | G34: 2 | H34: 2 | I34: Prototype Link
B35: Rules | C35: Score weights | D35: As a clinical admin, I can set overall/domain score weights and algorithm version. | E35: Removed | F35: Yes | G35: 4 | H35: 6
B36: Forecast | C36: Forecast thresholds | D36: As a clinical admin, I can set forecast confidence thresholds and minimum data points. | E36: Removed | F36: Yes | G36: 2 | H36: 4
B37: Eval | C37: Test-case library | D37: As the Medical Director, I can author graded clinical test cases. (Immaging and lab order) | E37: Retained | F37: Yes | G37: 4 | H37: 6 | I37: Prototype Link
B38: Eval | C38: Test-Case List | D38: As the Medical Director, I should see all clinical test cases with their area, severity, expected outcome and latest result, and search, filter, select and export them. | E38: New | G38: 2 | H38: 2 | I38: Prototype Link
B39: Eval | C39: Regression gate | D39: As an engineer, a change is regression-tested before it ships. | E39: Removed | F39: Yes | G39: 2 | H39: 6
B40: Eval | C40: Version log | D40: As an engineer, prompt/model/protocol versions are logged for reproducibility. | E40: Removed | F40: Yes | G40: 2 | H40: 4
B41: Evidence | C41: Source expiry & re-review | D41: As a HOL clinical admin, sources carry expiration/review dates so a guideline update or safety notice triggers re-review. | E41: Removed | F41: Yes | G41: 2 | H41: 2
A42: OPERATIONS CONSOLE
B43: Integration health | C43: Monitor connections | D43: As ops, I can see the health of EMR, Terra, and partner connections. | E43: Retained | F43: Yes | G43: 4 | H43: 6 | I43: Not Req
B44: Integration health | C44: Failed imports | D44: As ops, I can see and retry failed imports. | E44: Retained | F44: Yes | G44: 2 | H44: 6 | I44: Not Req
B45: Integration health | C45: Sync status | D45: As ops, I can see per-patient sync timestamps. | E45: Retained | F45: Yes | G45: 2 | H45: 4 | I45: Not Req
B46: Parsing review | C46: Verification queue | D46: As ops, I can review low-confidence document extractions. | E46: Retained | F46: Yes | G46: 4 | H46: 6 | I46: Not Req
B47: Parsing review | C47: Correct & approve | D47: As ops, I can correct and approve an extraction. | E47: Retained | F47: Yes | G47: 2 | H47: 4 | I47: Not Req
B48: Settings | C48: Settings Overview | D48: As a Super Admin, I should see all settings areas in one place and open any of them. | E48: New | F48: Yes | G48: 2 | H48: 2 | I48: Prototype Link
B49: AI | C49: AI Credit Allowance | D49: As a Super Admin, I can set how much free and paid patients can use Ask Inlay, and over what period. | E49: New | F49: Yes | G49: 2 | H49: 2 | I49: Prototype Link
B50: Partners | C50: Partner List | D50: As a Super Admin, I should see all partners with their type, locations, services, contact and status, and search, filter | E50: New | F50: Yes | G50: 2 | H50: 2 | I50: Prototype Link
B51: Partners | C51: Add & Edit Partner | D51: As a Super Admin, I can add a partner and edit its details, locations, services and contact person. | E51: New | F51: Yes | G51: 4 | H51: 2 | I51: Prototype Link
B52: Consent | C52: Consent status | D52: As ops, I can see consent status per patient and scope. | E52: Removed | F52: No | G52: 2 | H52: 4
B53: Audit | C53: Audit logs | D53: As ops, I can view the immutable audit trail of access and edits and export the audit log | E53: Retained | F53: Yes | G53: 4 | H53: 6 | I53: Prototype Link
B54: Security | C54: User & access admin | D54: As a system admin, I can view security, MFA, and break-glass access (logged). | E54: Retained | F54: Yes | G54: 4 | H54: 6 | I54: Not Req
A55: PRACTICES
B56: Practice List | C56: Practice List | D56: As a Super Admin, I should see all practices with their key details and conversion, and search, filter and page through them. | E56: New | F56: Yes | G56: 2 | H56: 2 | I56: Prototype Link
B57: Tenancy | C57: Tenant admin | D57: As a Super Admin, I should be able to add a practice (a new tenant) with its details, contact, location, messaging number and the features it can use. | E57: Modified | F57: Yes | G57: 2 | H57: 4 | I57: Prototype Link
B58: Practice Details | C58: Practice Overview | D58: As a Super Admin, I should be able to open a practice and see its adoption summary and full information. | E58: New | F58: Yes | G58: 2 | H58: 2 | I58: Prototype Link
B59: Practice Details | C59: Edit & Deactivate Practice | D59: As a Super Admin, I should be able to edit a practice’s details and feature access, or deactivate the practice. | E59: New | F59: Yes | G59: 2 | H59: 2 | I59: Prototype Link
B60: Practice Details | C60: Providers & Users | D60: As a Super Admin, I should see a practice’s providers with their enrolment progress, and its users with their role and activity. | E60: New | F60: Yes | G60: 2 | H60: 2 | I60: Prototype Link
A61: NOTIFICATIONS
B62: Notifications | C62: Ops alerts | D62: As HOL ops, I receive alerts for integration failures and parsing-review items. | E62: Retained | F62: Yes | G62: 2 | H62: 4 | I62: Not Req
A63: BACK OFFICE & CATALOG
B64: Back office | C64: Add-on catalog | D64: As HOL ops, I can manage the add-on catalog and pricing. | E64: Retained | F64: Yes | G64: 4 | H64: 6 | I64: Prototype Link
B65: Back office | C65: Commission tracking | D65: As HOL ops, I can track partner commissions. | E65: Retained | F65: Yes | G65: 2 | H65: 4 | I65: Not Req
B66: Back office | C66: Usage & billing admin | D66: As HOL ops, I can administer usage, billing and revenue-share settlement. | E66: Retained | F66: Yes | G66: 4 | H66: 8 | I66: Prototype Link
A67: BILLING
B68: Billing | C68: Billing Dashboard | D68: As a Super Admin, I can see billing KPIs and items that need attention. | E68: New | F68: Yes | G68: 2 | H68: 2 | I68: Not Req
B69: Billing | C69: Pricing & catalog config | D69: As HOL ops, I can configure pricing, membership tiers and the add-on catalog. | E69: Retained | F69: Yes | G69: 4 | H69: 6 | I69: Prototype Link
B70: Billing | C70: Test & Imaging Catalogue | D70: As a Super Admin, I can add lab and imaging tests with their vendor, category, code and vendor details. | E70: New | F70: Yes | G70: 2 | H70: 2 | I70: Prototype Link
B71: Billing | C71: Price & Margin Calculation | D71: As a Super Admin, I can set a test’s price from the vendor rate plus margin, regional override and tax, and see the provider price, patient price and vendor payout. | E71: New | F71: Yes | G71: 2 | H71: 4 | I71: Prototype Link
B72: Billing | C72: Membership & AI Allowance | D72: As a Super Admin, I can set monthly and annual membership prices, discounts and each plan’s AI chat allowance, and see active users per plan. | E72: New | F72: Yes | G72: 2 | H72: 2 | I72: Prototype Link
B73: Billing | C73: Practice Billing Terms | D73: As a Super Admin, I can set each practice’s invoice frequency, payment terms, grace period and late fee. | E73: New | F73: Yes | G73: 2 | H73: 2 | I73: Prototype Link
B74: Billing | C74: Practice Invoices | D74: As a Super Admin, I can generate, download and share practice invoices with a full breakdown, using internal and practice templates. | E74: New | F74: Yes | G74: 4 | H74: 4 | I74: Prototype Link
B75: Billing | C75: Refunds & adjustments | D75: As HOL ops, I can issue refunds to the original payment method, apply credits for orders that didn’t complete, and make billing adjustments. | E75: Modified | F75: Yes | G75: 2 | H75: 4 | I75: Prototype Link
B76: Billing | C76: Usage metering & reconcile | D76: As HOL ops, I can meter AI usage and reconcile it against billing. | E76: Retained | F76: Yes | G76: 4 | H76: 6 | I76: Prototype Link
B77: Billing | C77: Sales Tax | D77: As the system, I calculate sales tax at checkout and produce reports for filing. | E77: New | F77: Yes | G77: 2 | H77: 2 | I77: Not Req
B78: Billing | C78: Billing reports | D78: As HOL ops, I can produce billing and revenue reports, including vendor payouts, revenue by lab and imaging, cancellation and late-fee losses, overdue practices, and totals by channel. | E78: Modified | F78: Yes | G78: 2 | H78: 4 | I78: Prototype Link
B79: Billing | C79: Seller-of-record config | D79: As HOL ops, I can configure the seller-of-record per practice. | E79: Removed | F79: No | G79: 2 | H79: 4
B80: Billing | C80: Revenue-share settlement | D80: As HOL ops, I can run and review revenue-share settlement across practices. | E80: Retained | F80: Yes | G80: 4 | H80: 6 | I80: Not Req
A81: GOVERNANCE & VALIDATION TOOLING
B82: Governance | C82: Clinical safety test set | D82: As a HOL clinical admin, I maintain a representative clinical safety test set (rare conditions, conflicting/missing data, urgent, special populations) for release gating. | E82: Retained | F82: Yes | G82: 4 | H82: 8 | I82: Prototype Link
B83: Governance | C83: Release-gate checklist | D83: As a HOL clinical admin, I can confirm minimum release requirements (intended use, provenance, policy engine, hard stops, firewall, privacy) are met before a pilot. | E83: Retained | F83: Yes | G83: 4 | H83: 6 | I83: Not Req
B84: Governance | C84: Incident & correction workflow | D84: As a HOL clinical admin, I can classify, investigate and resolve safety incidents and patient/physician corrections with closed-loop status. | E84: Retained | F84: Yes | G84: 4 | H84: 8 | I84: Not Req
E86: Retained | G86: =SUMIF(E4:E84,E86,G4:G84) | H86: =SUMIF(E4:E84,E86,H4:H84)
E87: Modified | G87: =SUMIF(E5:E85,E87,G5:G85) | H87: =SUMIF(E4:E84,E87,H4:H84)
E88: New | G88: =SUMIF(E4:E84,E88,G4:G84) | H88: =SUMIF(E4:E84,E88,H4:H84)
E89: Removed | G89: =SUMIF(E4:E84,E89,G4:G84) | H89: =SUMIF(E4:E84,E89,H4:H84)
E90: Total | G90: =SUM(G86:G88) | H90: =SUM(H86:H88)

Sheet Physician Portal  Provider port
G1: =SUM(G3:G153) | H1: =SUM(H3:H153)
A2: SR.NO | B2: MODULE | C2: CAPABILITY | D2: USER STORY | E2: STATUS | F2: REQUIRED | G2: FRONT END | H2: BACK END | I2: DESIGN LINK | J2: COMMENT
A3: Provider Onboarding & Login
B4: Auth | C4: Login & MFA | D4: As a Provider, I should be able to sign in with my Organization ID, email and password, with an option to remember me on the same device, and enter a code from my authenticator app to complete sign-in when asked (once a week and on a new device). | E4: Retained | F4: Yes | G4: 2 | H4: 2 | I4: Prototype Link
B5: Onboarding | C5: Practice onboarding | D5: As an admin, I can onboard the practice and its physicians. | E5: Retained | F5: Yes | G5: 4 | H5: 6 | I5: Prototype Link
B6: Invitation | C6: Invitation Email | D6: As a Provider, I should receive an invitation email from my practice’s clinic manager with my role, my email, a one-time activation code and an “Activate account” button, so that I can join the provider portal. | E6: New | F6: Yes | G6: 2 | H6: 2 | I6: Prototype Link
B7: Activate Account | C7: Activate Account & Set Password | D7: As a Provider, I should be able to activate my account with the code from my email and create my password. | E7: Retained | F7: Yes | G7: 2 | H7: 2 | I7: Prototype Link
B8: Activate Account | C8: Two-Factor Setup | D8: As a Provider, I should be able to set up two-factor authentication with an authenticator app so that my account is protected. | E8: New | F8: Yes | G8: 2 | H8: 2 | I8: Prototype Link
B9: Forgot Password | C9: Forgot Password & Reset Code | D9: As a Provider, I should be able to request a password reset code to my email, verify it, and resend it if I didn’t receive it. | E9: New | F9: Yes | G9: 2 | H9: 2 | I9: Prototype Link
A10: Dashboard
B11: Dashboard | C11: Enrollment & activation | D11: As a practice admin, I can see patient enrollment and activation metrics. | E11: Retained | F11: Yes | G11: 4 | H11: 6 | I11: Prototype Link
B12: Dashboard | C12: Engagement metrics | D12: As a practice admin, I can see patient engagement across my panel. | E12: Removed | F12: Yes | G12: 2 | H12: 4
B13: Dashboard | C13: Outcome changes | D13: As a practice admin, I can see outcome changes over time for my patients. | E13: Removed | F13: Yes | G13: 4 | H13: 6
B14: Dashboard | C14: Alert volume | D14: As a Provider, I should see one list of items waiting on me and act on each one directly (review, open or reply). | E14: Modified | F14: Yes | G14: 2 | H14: 4 | I14: Prototype Link
B15: Dashboard | C15: Physician review time | D15: As a practice admin, I can see average physician review time per report. | E15: Removed | F15: Yes | G15: 2 | H15: 4
B16: Dashboard | C16: Value & renewal metrics | D16: As a practice admin, I can see value and renewal-supporting metrics. | E16: Removed | F16: Yes | G16: 2 | H16: 4
B17: Dashboard | C17: My Tasks | D17: As a Provider, I want to view my open tasks, upcoming appointments, messages, and urgent tasks on my dashboard. | E17: New | F17: Yes | G17: 2 | H17: 2 | I17: Prototype Link
B18: Dashboard | C18: Today’s Schedule | D18: As a Provider, I should see today’s visits with time, patient, visit type and status, and the patient in the room now, with options to open their details or chart. | E18: New | F18: Yes | G18: 2 | H18: 2 | I18: Prototype Link
B19: Worklist | C19: Abnormal Results | D19: As a Provider, I should see each abnormal result’s priority, test, result, source (with an “Outside” tag) and resulted date, and mark it as reviewed. | E19: New | F19: Yes | G19: 2 | H19: 2 | I19: Prototype Link
A20: Patients
B21: Patient | C21: Patient list | D21: As a Provider, I should see my practice’s patients with risk level, ID, name, age and bio age, contact, location, primary provider, status, last interaction and last sync, and open a patient’s dashboard from the list. | E21: Modified | F21: Yes | G21: 4 | H21: 6 | I21: Prototype Link
B22: Priority queue | C22: Sorted work queue | D22: As a physician, I can see critical/high/watch/stable sorted by severity & change. | E22: Retained | F22: Must Have | G22: 4 | H22: 6 | I22: Prototype Link
B23: Priority queue | C23: Filter & triage | D23: As a physician, I can filter and triage the queue. | E23: Retained | F23: Must Have | G23: 2 | H23: 4 | I23: Prototype Link
B24: Add Patient | C24: Add Patient Form | D24: As a Provider, I should be able to enter the patient’s basic details, additional details and emergency contact. | E24: New | F24: Yes | G24: 4 | H24: 2 | I24: Prototype Link
B25: Patient | C25: Enroll & assign | D25: As a Provider, I should be able to start adding a patient with their key details and assign the patient’s location and primary provider. | E25: Retained | F25: Yes | G25: 4 | H25: 6 | I25: Prototype Link
B26: Add Patient | C26: Duplicate Patient Check | D26: As a Provider, I should be told if the patient I’m adding already exists, so that no duplicate record or second invite is created. | E26: New | F26: Yes | G26: 2 | H26: 2 | I26: Prototype Link
B27: Edit Patient | C27: Edit Patient | D27: As a Provider, I should be able to edit a patient’s details, profile picture, care team and emergency contacts (email is read-only). | E27: New | F27: Yes | G27: 2 | H27: 2 | I27: Prototype Link
B28: Bulk Add Patients | C28: Template & Upload | D28: As a Provider, I should be able to download a CSV template and upload a filled file to add patients in bulk. | E28: New | F28: Yes | G28: 2 | H28: 2 | I28: Prototype Link
B29: Bulk Add Patients | C29: Add bulk patient | D29: As a Provider, I should be able to review the uploaded rows by status (new, already on file, to reactivate, needs review, errors) and import them, with the new patients added as “Invited”. | E29: New | F29: Yes | G29: 4 | H29: 2 | I29: Prototype Link
B30: Patient | C30: Refer & invite patient | D30: As a Provider, I should be able to save the new patient so that an invitation is sent and they appear as “Invited”. | E30: Retained | F30: Yes | G30: 2 | H30: 4 | I30: Prototype Link
B31: Patient | C31: Patient’s HOL summary | D31: As a physician, I can receive the patient’s HOL summary directly in my existing medical records system, so I don’t have to log into a separate portal to see it | E31: Removed | F31: Yes | G31: 4 | H31: 6
B32: Patients | C32: Tabs, Search, Filters & Pagination | D32: As a Provider, I should be able to view patients by status tab, search the list, filter it (including by sync failed) and page through it. | E32: New | F32: Yes | G32: 2 | H32: 2 | I32: Prototype Link
B33: Patients | C33: Select & Export | D33: As a Provider, I should be able to select patients and export the patient list to Excel. | E33: New | F33: Yes | G33: 2 | H33: 2 | I33: Prototype Link
A34: Task
B35: Tasks | C35: Task List | D35: As a Provider, I should see tasks with their priority, ID, type, patient, assignee, title, status and due date, with overdue tasks highlighted, and open a task’s details. | E35: New | F35: Must Have | G35: 2 | H35: 2 | I35: Prototype Link
B36: Tasks | C36: Tabs, Search, Filter | D36: As a Provider, I should be able to switch between All tasks and My tasks, search and filter the list, and page through it. | E36: New | F36: Must Have | G36: 2 | H36: 2 | I36: Prototype Link
B37: Tasks | C37: Select Tasks | D37: As a Provider, I should be able to select one, several or all tasks, see how many are selected, and clear my selection. | E37: New | F37: Must Have | G37: 2 | H37: 2 | I37: Prototype Link
B38: Tasks | C38: Bulk Mark Complete | D38: As a Provider, I should be able to mark the selected tasks complete in one action. | E38: New | F38: Must Have | G38: 2 | H38: 2 | I38: Prototype Link
B39: Add Task | C39: Add Task | D39: As a Provider, I should be able to add a task with its type, priority, assignee, due date and time, and title, optionally linked to a patient with a description, and see a confirmation once it’s added. | E39: New | F39: Must Have | G39: 2 | H39: 2 | I39: Prototype Link
A40: Scheduling
B41: Scheduling | C41: Appointments view | D41: As a physician, I can view appointments pulled from the EHR by day, week or month, as a calendar or a list, move between dates (Today, previous, next) and see the appointment count, with filters (type, status, in-person/virtual); view only. | E41: Modified | F41: Must Have | G41: 2 | H41: 2 | I41: Prototype Link
B42: Scheduling | C42: Appointments – Calendar View | D42: As a physician, I can view appointments pulled from the EHR on a calendar by day, week or month, move between dates (Today, previous, next) and see the appointment count; view only. | E42: New | F42: Must Have | G42: 4 | H42: 2 | I42: Prototype Link
B43: Scheduling | C43: Appointments – List View | D43: As a physician, I can view appointments as a list by day, week or month, with each appointment’s patient, type, in-person or virtual, reason and status, and page through them; view only. | E43: New | F43: Must Have | G43: 2 | H43: 2 | I43: Prototype Link
B44: Scheduling | C44: Appointment Details & Filters | D44: As a physician, I can filter appointments by status, type and in-person or virtual, and open an appointment to see its details and the patient’s contact, then open their chart. | E44: New | F44: Must Have | G44: 2 | H44: 2 | I44: Prototype Link
A45: Communication
B46: Communication | C46: Conversation List | D46: As a Provider, I should see my conversations with the other provider’s name, last message preview, time and unread count, with the most recent at the top. | E46: New | F46: Must Have | G46: 2 | H46: 2 | I46: Prototype Link
B47: Communication | C47: Search & Filter Conversations | D47: As a Provider, I should be able to search my conversations and filter them by All or Unread. | E47: New | F47: Must Have | G47: 2 | H47: 2 | I47: Prototype Link
B48: Communication | C48: Conversation View | D48: As a Provider, I should be able to open a conversation and see the other provider’s details and the messages grouped by date, with sender and time. | E48: New | F48: Must Have | G48: 2 | H48: 2 | I48: Prototype Link
B49: Communication | C49: Send Message | D49: As a Provider, I should be able to type and send a message, with the conversation moving to the top of my list. | E49: New | F49: Must Have | G49: 2 | H49: 2 | I49: Prototype Link
B50: Communication | C50: Voice to Text | D50: As a Provider, I should be able to dictate a message using the microphone. | E50: New | F50: Must Have | G50: 2 | H50: 2 | I50: Prototype Link
B51: Communication | C51: Attach & Share Documents | D51: As a Provider, I should be able to attach a document to a message and download documents shared in the chat. | E51: New | F51: Must Have | G51: 2 | H51: 4 | I51: Prototype Link
B52: Communication | C52: Reply to a Message | D52: As a Provider, I should be able to see replies with the earlier message quoted above them. | E52: New | F52: Must Have | G52: 2 | H52: 2 | I52: Prototype Link
B53: Communication | C53: Reactions | D53: As a Provider, I should be able to react to a message and see the reaction count. | E53: New | F53: Must Have | G53: 2 | H53: 2 | I53: Prototype Link
B54: New Chat | C54: Start New Chat | D54: As a Provider, I should be able to start a new chat by searching for and selecting a provider. | E54: New | F54: Must Have | G54: 2 | H54: 2 | I54: Prototype Link
A55: REPORT REVIEW & SIGN-OFF
B56: Report review | C56: Review AI report | D56: As a physician, I can open the AI-drafted report with evidence links. | E56: Removed | G56: 12 | H56: 12
B57: Report review | C57: Approve / edit / reject | D57: As a physician, I can approve, edit, reject, or request a repeat test. | E57: Removed | G57: 8 | H57: 8
B58: Report review | C58: Release to patient | D58: As a physician, sign-off releases the report to the patient. | E58: Removed | G58: 4 | H58: 4
B59: Report review | C59: Batch & review time | D59: As a physician, I can batch unflagged reports; review time is tracked. | E59: Removed | G59: 4 | H59: 4
A60: REPORT
B61: Reports | C61: Reports module | D61: As a user, I can run reports with filters (period, month, location), see KPIs compared with the previous period and a breakdown by provider with totals, and export or print. | E61: Retained | G61: 4 | H61: 4 | I61: Prototype Link
B62: Reports | C62: Patient Engagement Report | D62: As a user, I can see patients, invited, active, declined and inactive counts and the active rate by provider. | E62: Retained | G62: 2 | H62: 2 | I62: Prototype Link
B63: Reports | C63: Membership Conversion Report | D63: As a user, I can see free patients, how many viewed the upgrade, new members, conversion rate and new revenue by provider. | E63: Retained | G63: 2 | H63: 2 | I63: Prototype Link
B64: Reports | C64: Result Review Turnaround Report | D64: As a user, I can see results received, out of range, reviewed, the percentage reviewed within 48 hours and average time to review by provider. | E64: Retained | G64: 2 | H64: 2 | I64: Not Req
B65: Reports | C65: Care Gap Closure Report | D65: As a user, I can see care gaps found, outreach sent, gaps closed and closure rate by provider. | E65: Retained | G65: 2 | H65: 2 | I65: Not Req
B66: Reports | C66: Medication Reconciliation Report | D66: As a user, I can see medication changes flagged, confirmed, waiting and the confirmed rate by provider. | E66: Retained | G66: 2 | H66: 2 | I66: Not Req
B67: Reports | C67: Baseline Tests Report | D67: As a user, I can see baseline tests ordered, scheduled and completed, the completion rate and average days to complete by provider. | E67: Retained | G67: 2 | H67: 2 | I67: Not Req
B68: Reports | C68: Task Completion Report | D68: As a user, I can see tasks created, completed and overdue and the completion rate by provider. | E68: Retained | G68: 2 | H68: 2 | I68: Not Req
B69: Reports | C69: Practice-level dashboard | D69: As a physician, I can see engagement across my panel (office visits, virtual visits, MyChart messages, refills) combined with clinical status, and who has had little engagement in 3 months. | E69: Retained | G69: 2 | H69: 4 | I69: Prototype Link
B70: Reports | C70: Employer reports | D70: As a physician, I can filter reports by employer to see participation, encounter totals with breakdown (office visits, virtual visits, etc.) per employee and for the whole group, outcome changes, and optimized vs non-optimized patients, all de-identified. | E70: Retained | G70: 2 | H70: 4 | I70: Prototype Link
A71: PATIENT CHARTING
B72: Record | C72: Full longitudinal record | D72: As a physician, I can see the patient’s full health history over time, including where each result came from and its original value | E72: Retained | F72: Yes | G72: 4 | H72: 6 | I72: Prototype Link
B73: AI Chart Summary | C73: Trends & flags | D73: As a Provider, I should see the patient’s out-of-range results and trends to watch, each with its latest value and a mini trend. | E73: Modified | F73: Must Have | G73: 8 | H73: 8 | I73: Prototype Link
B74: AI Chart Summary | C74: Suggested follow-up tests | D74: As a physician, I can see sourced follow-up-test suggestions. | E74: Retained | F74: Must Have | G74: 8 | H74: 8 | I74: Not Req
B75: AI Chart Summary | C75: Panel gaps | D75: As a physician, I can see declining markers and missed testing across my panel. | E75: Retained | F75: Must Have | G75: 8 | H75: 8 | I75: Not Req
B76: Patient Header | C76: Patient Header | D76: As a Provider, I should see the patient’s photo, name, ID, age, phone, key conditions, and last and next visit at the top of every chart page, and be able to expand or collapse it. | E76: New | F76: Must Have | G76: 4 | H76: 2 | I76: Prototype Link
B77: Summary | C77: One-page summary | D77: As a physician, I can see conditions, meds, top changes, alerts, labs, questions on one screen and patient’s last sync status. | E77: Retained | F77: Yes | G77: 6 | H77: 6 | I77: Prototype Link
B78: Patient Header | C78: Add patient Label | D78: As a Provider, I should be able to add a label to the patient from the header. | E78: New | F78: Must Have | G78: 2 | H78: 2 | I78: Prototype Link
B79: Dashboard | C79: Important Updates | D79: As a Provider, I should see the patient’s important updates since the last visit, grouped into “Action needed” and “For review”, with the reason for each, and open any update. | E79: New | F79: Must Have | G79: 4 | H79: 2 | I79: Prototype Link
B80: Overview | C80: Face Sheet | D80: As a Provider, I should see the patient’s face sheet with allergies, diagnoses, medications, encounters, appointments, vitals and lab results, and open the full section from any card. | E80: New | F80: Must Have | G80: 6 | H80: 4 | I80: Prototype Link
B81: Overview | C81: Print Chart | D81: As a Provider, I should be able to print the face sheet or save it as a PDF. | E81: New | F81: Must Have | G81: 2 | H81: 2 | I81: Prototype Link
B82: Overview | C82: Timeline | D82: As a Provider, I should see the patient’s history as a timeline of events grouped by date, and filter it by event type. | E82: New | F82: Must Have | G82: 4 | H82: 2 | I82: Prototype Link
B83: Care Plan | C83: Edit Plan | D83: As a Provider, I should be able to edit the care plan as a new version, adding, changing or deleting plans and items. | E83: New | F83: Must Have | G83: 6 | H83: 4 | I83: Prototype Link
... B103: Patient Chart | C103: Discharge or Deactivate Patient | D103: As a Provider, I should be able to discharge or deactivate a patient from their profile. | E103: New | F103: Must Have | G103: 2 | H103: 2 | I103: Prototype Link
A104: Plan builder
B105: Plan builder | C105: Goals & interventions | D105: As a physician, I can set goals, interventions, cadence, and success measures. | E105: Removed | F105: Must Have | G105: 6 | H105: 6
B106: Plan builder | C106: Approve goals | D106: As a physician, I can approve patient goals. | E106: Removed | F106: Must Have | G106: 2 | H106: 4
A107: ALERTS & SAFETY
B108: Alerts | C108: Alert detail | D108: As a physician, I can see triggering data, rule version, confidence, and disposition. | E108: Retained | F108: Must Have | G108: 6 | H108: 6 | I108: Not Req
B109: Alerts | C109: Acknowledge & route | D109: As a physician, I can acknowledge an alert and record the action. | E109: Removed | F109: Must Have | G109: 6 | H109: 6
A110: BILLING
B111: Billing | C111: Revenue-share statements | D111: As a practice admin, I can view revenue-share statements for my practice. | E111: Removed | F111: Must Have | G111: 8 | H111: 8
B112: Billing | C112: Physician review fee | D112: As a practice admin, I can see the per-review physician fee earned. | E112: Removed | F112: Must Have | G112: 8 | H112: 8
B113: Billing | C113: Practice Invoices | D113: As a Clinic Manager, I can see my practice’s invoices for every month and download the statment and pay for it. | E113: Modified | F113: Must Have | G113: 2 | H113: 2 | I113: Prototype Link
B114: Billing | C114: Invoice Details | D114: As a Clinic Manager, I can open an invoice to see its full breakdown by test, patient, facility and price, with any carried credit, and download it as a PDF. | E114: New | F114: Must Have | G114: 2 | H114: 4 | I114: Prototype Link
B115: Billing | C115: Pay Invoice & Raise Query | D115: As a Clinic Manager, I can pay an invoice, or raise a query about it, with “Pay now” hidden when auto-debit is on. | E115: New | F115: Must Have | G115: 2 | H115: 2 | I115: Not Req
B116: Orders | C116: Order a Test | D116: As a Provider, I can order a practice-paid test or scan for a patient from the catalogue at the provider price, and follow it to the result. | E116: New | F116: Must Have | G116: 2 | H116: 4 | I116: Prototype Link
B117: Orders | C117: Order Details | D117: As a Provider, I can open an order and see the patient, tests, lab or facility, priority, collection date, price and its status from ordered to result. | E117: New | F117: Must Have | G117: 2 | H117: 2 | I117: Prototype Link
A118: PROVIDER SETTINGS
B119: Billing | C119: Entitlements | D119: As a practice admin, I can see what the membership covers vs paid add-ons. | E119: Removed | F119: Must Have | G119: 8 | H119: 8
...

Sheet Patient App
G1: =SUM(G3:G151) | H1: =SUM(H3:H151)
A2: SR.NO | B2: MODULE | C2: CAPABILITY | E2: STATUS | F2: REQUIRED | G2: FRONT END | H2: BACK END | I2: Frontend | J2: Backend | K2: DESIGN LINK | L2: COMMENT
A3: ONBOARDING & CONSENT
B4: Onboarding & consent | C4: Register via invite | D4: As a patient, I can register through the secure invite link. | E4: Retained | F4: Yes | G4: 2 | H4: 4 | I4: 4 | J4: 6 | K4: Prototype Link
B5: Patient Web – Onboarding & Consent | C5: Invitation Email | D5: As a Patient, I should receive an invitation email from my practice with a one-time activation code and an “Activate account” button. The code works once and expires in 48 hours. | E5: New | F5: Yes | G5: 4 | H5: 4 | I5: 2 | J5: 4 | K5: Not Req
B6: Patient Web – Onboarding & Consent | C6: Activate Account | D6: As a Patient, I should be able to open the invite link in my system and activate my account by entering my email, date of birth and the 6-digit code from my invitation. | E6: New | F6: Yes | G6: 4 | H6: 4 | I6: 2 | J6: 4 | K6: Prototype Link
B7: Patient Mobile – Onboarding & Consent | C7: Download App | D7: As a Patient, I should be able to download the Inlay Health app from the App Store or Google Play using the links in my invitation email. | E7: New | F7: Yes | G7: 0 | H7: 2 | K7: Not Req
B8: Onboarding & consent | C8: Identity verification | D8: As a patient, I can verify my identity at onboarding. | E8: Retained | F8: Yes | G8: 2 | H8: 4 | I8: 6 | J8: 6 | K8: Prototype Link
B9: Onboarding & consent | C9: 2FA / login | D9: As a patient, I can log in with 2FA and biometrics. | E9: Retained | F9: Yes | G9: 6 | H9: 4 | I9: 6 | J9: 6 | K9: Prototype Link
B10: Patient Web – Onboarding & Consent | C10: Create Password | D10: As a Patient, I should be able to create my password by entering and confirming it, with an option to show or hide what I type. | E10: Retained | F10: Yes | H10: 2 | I10: 6 | J10: 6 | K10: Prototype Link
B11: Patient Mobile – Onboarding | C11: First-Time Setup | D11: As a Patient signing in for the first time, I should be guided step by step to confirm my details, connect my health records and choose how Inlay contacts me about my care. | E11: New | F11: Yes | G11: 10 | H11: 8 | K11: Prototype Link
B12: Patient Mobile – Onboarding | C12: Record Building & Ready | D12: As a Patient, I should see what my free account does for me and tell Inlay what matters most while my record builds, until my record is ready. | E12: New | F12: Yes | G12: 6 | H12: 4 | K12: Prototype Link
B13: Patient Web – Onboarding & Consent | C13: Forgot Password | D13: As a Patient, I should be able to click “Forgot password?” on the sign-in screen to reset my password. | E13: Retained | F13: Yes | G13: 2 | H13: 4 | K13: Prototype Link
B14: Patient Web – Onboarding & Consent | C14: Log Out | D14: As a Patient, I should be able to log out of the app. | E14: Retained | F14: Yes | G14: 2 | H14: 4 | I14: 6 | J14: 6 | K14: Prototype Link
B15: Onboarding & consent | C15: Sign consent | D15: As a patient, I can review and sign consent before any data is collected. | E15: Retained | F15: Yes | G15: 2 | H15: 4 | I15: 4 | J15: 6 | K15: Prototype Link
B16: Onboarding & consent | C16: Withdraw consent | D16: As a patient, I can withdraw consent and stop the data pull. | E16: Retained | F16: Yes | G16: 2 | H16: 4 | K16: Prototype Link
A17: INTAKE & GOALS
B18: Intake & goals | C18: AI-guided intake | D18: As a patient, I can complete an AI-guided intake (goals, history, habits). | E18: Removed | F18: Yes | G18: 4 | H18: 6
B19: Intake & goals | C19: Save & resume | D19: As a patient, I can save and resume my intake. | E19: Removed | F19: Yes | G19: 4 | H19: 6 | I19: =SUMIFS(I32:I44,G32:G44,G19) | J19: =SUMIFS(J32:J44,G32:G44,G19)
B20: Intake & goals | C20: AI-proposed goals | D20: As a patient, I should be able to view AI-proposed goals from my data. | E20: Retained | F20: Yes | G20: 4 | H20: 6 | K20: Prototype Link
B21: Intake & goals | C21: Select goals | D21: As a patient, I can select goals; they stay pending physician approval. | E21: Removed | F21: Yes | G21: 4 | H21: 6
A22: DATA CONNECTIONS
B23: Data connections | C23: Authorize EMR | D23: As a patient, I can authorize EMR access from the app. | E23: Removed | F23: Yes | G23: 4 | H23: 6
B24: Data connections | C24: Multi-hospital auth | D24: As a patient, I can authorize multiple hospitals separately. | E24: Removed | F24: Yes | G24: 4 | H24: 6
B25: Data connections | C25: Revoke access | D25: As a patient, I can revoke access anytime. | E25: Removed | F25: Yes | G25: 2 | H25: 4
B26: Data connections | C26: Updates About Your Care | D26: As a Patient, I should be able to choose whether Inlay can text, call or email me about my care, and agree to the messaging terms. | E26: New | F26: Yes | G26: 2 | H26: 4 | K26: Prototype Link
B27: Data connections | C27: Record Building & Ready | D27: As a Patient, I should see my record being built from each source after connecting, be able to go to my dashboard while it builds, and see a summary by type once my record is ready. | E27: New | F27: Yes | G27: 8 | H27: 6 | K27: Prototype Link
B28: Data connections | C28: Connect device (Terra) | D28: As a patient, I can connect a wearable via Terra. | E28: Retained | F28: Yes | G28: 6 | H28: 6 | K28: Prototype Link
B29: Data connections | C29: Connection status | D29: As a patient, I can see device connection & sync status. | E29: Retained | F29: Yes | G29: 2 | H29: 2 | K29: Not Req
B30: Data connections | C30: Upload report | D30: As a patient, I can upload a DEXA/lab PDF; AI extracts the values. | E30: Removed | F30: No | G30: 4 | H30: 6
B31: Data connections | C31: Extraction preview | D31: As a patient, I can confirm extracted values before they are saved. | E31: Removed | F31: No | G31: 2 | H31: 4
A32: DASHBOARD
B33: Dashboard | C33: Overall & domain scores | D33: As a patient, I can see my overall HOL score and domain scores. | E33: Retained | F33: Yes | G33: 4 | H33: 6 | I33: 2 | J33: 4 | K33: Prototype Link
B34: Dashboard | C34: Top priorities & tasks | D34: As a patient, I can see my top priorities and today’s tasks. | E34: Retained | F34: Yes | G34: 2 | H34: 4 | K34: Prototype Link
B35: Dashboard | C35: Live data & trends | D35: As a patient, I can see near-real-time data and trend lines (no gate). | E35: Retained | F35: Yes | G35: 4 | H35: 6 | K35: Prototype Link
B36: Patient Mobile – Home | C36: Home Header | D36: As a Patient, I should see a greeting with my name and photo, and a notifications bell showing how many unread notifications I have. | E36: New | F36: Yes | G36: 8 | H36: 4 | I36: 4 | J36: 6 | K36: Prototype Link
B37: Patient Mobile – Home | C37: Bottom Navigation | D37: As a Patient, I should be able to move between Home, Record, To do and Upgrade from the bottom menu. | E37: New | F37: Yes | G37: 6 | H37: 2 | I37: 2 | J37: 4 | K37: Prototype Link
B38: Patient Mobile – Member Home | C38: Member App Tour | D38: As a Member, I should see a 3-step tour explaining the bottom menu (Home, Record, To do, Plan), the health assistant and my account. | E38: New | F38: Yes | G38: 6 | H38: 2 | K38: Prototype Link
B39: Patient Mobile – Home | C39: New Results | D39: As a Patient, I should see on Home when new results have arrived, and tap through to view them. | E39: New | F39: Yes | G39: 4 | H39: 4 | K39: Not Req
B40: Patient Mobile – Home | C40: Cancelled Membership | D40: As a Patient, I should still see my free health record on Home after I cancel my membership, with an option to uprade again | E40: New | F40: Yes | G40: 4 | H40: 6 | I40: 4 | J40: 6 | K40: Not Req
B41: Patient Mobile – Home | C41: Upcoming Appointments | D41: As a Patient, I should see my next upcoming appointment Details on Home with the to view every upcoming appointment. | E41: New | F41: Yes | G41: 4 | H41: 6 | I41: 4 | J41: 6 | K41: Prototype Link
B42: Patient Mobile – Home | C42: Your Medicines | D42: As a Patient, I should see my current medicines with the dose, how often I take them and who prescribed them, plus my supplements, and tap “See all” to view the full list. | E42: New | F42: Yes | G42: 6 | H42: 6 | I42: 4 | J42: 6 | K42: Prototype Link
B43: Patient Mobile – Home | C43: Notifications | D43: As a Patient, I should be able to open my notifications from Home, see what’s new, and go to the item each one is about. | E43: New | F43: Yes | G43: 4 | H43: 6 | K43: Prototype Link
A44: TO DO
B45: Patient Mobile – Member Home | C45: Today’s To-do | D45: As a Member, I should see today’s plan tasks (workout, meals, walk, blood pressure check) with their time and details, and a progress ring showing how much of today I’ve done. | E45: New | F45: Yes | G45: 6 | H45: 6 | I45: 2 | J45: 4 | K45: Prototype Link
B46: Patient Mobile – To Do | C46: Free To Do – Filters & Completed | D46: As a free Patient, I should be able to filter my to-do list by All, Overdue, Upcoming or Completed, with a count on each, and see the items I’ve done recently. | E46: New | F46: Yes | G46: 8 | H46: 6 | K46: Prototype Link
B47: Patient Mobile – To Do | C47: Book a Test Through Inlay | D47: As a Patient, I should be able to book a test my physician ordered through Inlay by choosing a location (with its price and first opening) and a time slot. | E47: New | F47: Yes | G47: 6 | H47: 8 | K47: Prototype Link
B48: Patient Mobile – to do | C48: Tests Scheduled and view | D48: As a Patient, I should see my scheduled tests with their date, time and location and details | E48: New | F48: Yes | G48: 6 | H48: 6 | K48: Prototype Link
B49: Patient Mobile – To Do | C49: Pay & Place Order | D49: As a Patient, I should be able to pay for the test with an available payment method and place the order. | E49: New | F49: Yes | H49: 8 | K49: Prototype Link
B50: Patient Mobile – To Do | C50: Booking Confirmation | D50: As a Patient, I should see a booking confirmation for my test that I can add to my calendar or get directions from. | E50: New | F50: Yes | H50: 6 | K50: Not Req
B51: Patient Mobile – To Do | C51: Member To Do – Today's To Do Overview | D51: As a Member, I should see the to-do items that need my attention, with how many are overdue, each item’s due date and reminder, and act on each one directly (book, call or check). | E51: New | F51: Yes | G51: 8 | H51: 6 | K51: Prototype Link
B52: Patient Mobile – To Do | C52: Member To Do – Upcoming & Booked | D52: As a Member, I should see my upcoming appointments and reviews, and my booked tests with their date, time, place and preparation instructions, and open any of them. | E52: New | F52: Yes | G52: 8 | H52: 6 | K52: Prototype Link
B53: Patient Mobile – To Do | C53: Member To Do – Filters & Completed | D53: As a Member, I should be able to filter my to-do list by All, Overdue, Upcoming or Completed, with a count on each, and see the items I’ve done recently. | E53: New | F53: Yes | G53: 8 | H53: 6 | K53: Prototype Link
A54: MY HEALTH RECORD & BIOMARKERS
B55: Health record | C55: Chronological record | D55: As a patient, I can view my longitudinal record (labs, vitals, meds, DEXA). | E55: Retained | F55: Yes | G55: 4 | H55: 6 | K55: Prototype Link
B56: Health record | C56: Biomarker tracker | D56: As a patient, I can view biomarkers with value, target, trend, status. | E56: Retained | F56: Yes | G56: 6 | H56: 6 | K56: Prototype Link
B57: Patient Mobile – Record | C57: Biomarker Details | D57: As a Patient, I should be able to open a biomarker and see its latest value against its range, how it has changed over time, and every result with its date and source. | E57: New | F57: Yes | G57: 6 | H57: 6 | K57: Prototype Link
B58: Patient Mobile – Record | C58: Record tabs Details | D58: As a Patient, I should be able to open any item in my record, such as an imaging report, visit, condition or procedure, and see its details and source. | E58: New | F58: Yes | G58: 4 | H58: 6 | K58: Prototype Link
B59: Patient Mobile – Record | C59: Record Sections | D59: As a Patient, I should be able to move between the sections of my record and see my conditions, visits, allergies, immunizations and procedures, and open any of them. | E59: New | F59: Yes | G59: 6 | H59: 6 | K59: Prototype Link
B60: Health record | C60: Gauge view & filters | D60: As a patient, I can see each marker on a gauge and filter by status. | E60: Removed | F60: No | G60: 4 | H60: 6
B61: Patient Mobile – Record | C61: Medicines | D61: As a Patient, I should see my medicines and supplements by status, open any of them to see its details and any record that lists it differently, and confirm how I take it. | E61: New | F61: Yes | G61: 6 | H61: 6 | K61: Prototype Link
B62: Patient Mobile – Record | C62: Add to Record – Supplement | D62: As a Patient, I should be able to add a supplement to my record by photo (taking one, choosing one or uploading a file) or by typing it in, review what was read and any interaction warning, and confirm how I take it. | E62: New | F62: Yes | G62: 6 | H62: 8 | K62: Prototype Link
B63: Patient Mobile – Record | C63: Add to Record – Allergy | D63: As a Patient, I should be able to add an allergy to my record by photo or by typing it in, review it and save it. | E63: New | F63: Yes | G63: 4 | H63: 6 | K63: Prototype Link
B64: Patient Mobile – Record | C64: Add to Record – Condition | D64: As a Patient, I should be able to add a condition to my record by photo or by typing it in, review it and save it. | E64: New | F64: Yes | G64: 2 | H64: 4 | K64: Prototype Link
B65: Patient Mobile – Record | C65: Add to Record – Visit | D65: As a Patient, I should be able to add a visit to my record by photo or by typing it in, review it and save it. | E65: New | F65: Yes | G65: 2 | H65: 4 | K65: Prototype Link
B66: Patient Mobile – Record | C66: Add to Record – Test Result | D66: As a Patient, I should be able to add a test result to my record by photo or by typing it in, review it and save it. | E66: New | F66: Yes | G66: 2 | H66: 6 | K66: Prototype Link
A67: PLAN & TASKS
B68: Plan & tasks | C68: Daily/weekly actions | D68: As a patient, I can see my lifestyle plan and tasks. | E68: Removed | F68: No | G68: 4 | H68: 6
B69: Plan & tasks | C69: Check-ins | D69: As a patient, I can complete morning/evening check-ins. | E69: Removed | F69: No | G69: 2 | H69: 4
B70: Plan & tasks | C70: Adherence logging | D70: As a patient, I can log adherence to my plan. | E70: Removed | F70: No | G70: 2 | H70: 4
B71: Plan & tasks | C71: Mindfulness & stress | D71: As a patient, I can access guided mindfulness and stress-management content. | E71: Removed | F71: No | G71: 4 | H71: 4
B72: Patient Mobile – Plan | C72: Plan Overview | D72: As a Member, I should see my personalized care plan for today, with each of today’s goals across my plan areas and how many I’ve completed, and move between Today, History, Progress and Outlook. | E72: New | F72: Yes | G72: 6 | H72: 6 | K72: Prototype Link
B73: Patient Mobile – Plan | C73: Today – Exercise – Session & Logging | D73: As a Member, I should be able to open today’s exercise session, watch how to do each move, and mark it done as written or log the parts I did, changed or skipped. | E73: New | F73: Yes | G73: 6 | H73: 6 | K73: Prototype Link
B74: Patient Mobile – Plan | C74: Today – Exercise – Easier Version or Own Programme | D74: As a Member, I should be able to ask Inlay for an easier version of today’s session by saying or typing why, or upload my own exercise programme to use in my plan. | E74: New | F74: Yes | G74: 6 | H74: 6 | K74: Prototype Link
B75: Patient Mobile – Plan | C75: Today – Eat – Today’s Meals & Logging | D75: As a Member, I should see today’s nutrition targets and the meals I’ve logged, and log a meal by photo and description (typed or spoken), by scanning a barcode, or by importing from another app. | E75: New | F75: Yes | G75: 6 | H75: 8 | K75: Prototype Link
B76: Patient Mobile – Plan | C76: Today – Eat – Diet Plan | D76: As a Member, I should see my daily nutrition targets, what I’ve logged so far today, today’s focus and my planned meals, and log any meal from there. | E76: New | F76: Yes | G76: 4 | H76: 6 | K76: Prototype Link
B77: Patient Mobile – Plan | C77: Today – Eat – Drinks & History | D77: As a Member, I should be able to log the drinks I had at one sitting, and see my eating and drinking trends over time against my targets and limits. | E77: New | F77: Yes | G77: 4 | H77: 4 | K77: Prototype Link
B78: Patient Mobile – Plan | C78: Today – Mind – Today’s Practice | D78: As a Member, I should be able to complete today’s guided mind practice or a shorter version, ask Inlay to swap a practice that isn’t working, or log my own practice instead. | E78: New | F78: Yes | G78: 6 | H78: 6 | K78: Prototype Link
B79: Patient Mobile – Plan | C79: Today – Medication | D79: As a Member, I should see today’s medicines and supplements with any interactions, mark doses taken, report a side effect to my physician, and add a new medicine or supplement to my record. | E79: New | F79: Yes | G79: 4 | H79: 6 | K79: Prototype Link
B80: Patient Mobile – Plan | C80: Today – Measure | D80: As a Member, I should be able to enter today’s body measurements with a guide on how to measure, skip today and tell Inlay why, or connect a scale or blood pressure cuff. | E80: New | F80: Yes | G80: 4 | H80: 6 | K80: Prototype Link
B81: Patient Mobile – Plan | C81: Today – Sleep | D81: As a Member, I should see last night’s sleep score and what made it up against my sleep goal, follow tonight’s sleep window, log or adjust my sleep, or connect a sleep device. | E81: New | F81: Yes | G81: 4 | H81: 6 | K81: Prototype Link
B82: Patient Mobile – Plan | C82: History – Overview | D82: As a Member, I should see yesterday’s overall score and each plan topic’s score against its goal, and open any of them for more detail. | E82: New | F82: Yes | G82: 4 | H82: 4 | K82: Prototype Link
B83: Patient Mobile – Plan | C83: History – Yesterday | D83: As a Member, I should see a summary of yesterday’s energy balance, nutrition, movement and plan tasks. | E83: New | F83: Yes | G83: 4 | H83: 4 | K83: Prototype Link
... B90: Patient Mobile – Plan | C90: Outlook – Projection | D90: As a Member, I should see where I’m likely to be by a future date if I keep my current pace, what the projection assumes, and ask Inlay where I’ll be if I stay the course. | E90: New | F90: Yes | G90: 4 | H90: 6 | K90: Prototype Link
A91: OPTIMIZATION PACKAGES/ PLAN
B92: Packages | C92: Enroll in package | D92: As a patient, I can enroll in a goal-specific optimization package (body composition, metabolic, or cardiovascular/lipid). | E92: Retained | F92: Yes | G92: 6 | H92: 6 | K92: Prototype Link
B93: Patient Mobile – Upgrade | C93: Start Your Plan | D93: As a Patient, I should be able to start setting up my personalized plan from the Upgrade tab. | E93: New | F93: Yes | G93: 6 | H93: 2 | K93: Prototype Link
B94: Patient Mobile – Upgrade | C94: You’re Enrolled | D94: As a Patient, I should see that I’m enrolled, my plan and price, what happens next and choose to schedule my tests now or later. | E94: New | F94: Yes | G94: 6 | H94: 6 | K94: Prototype Link
B95: Packages | C95: Bundled diagnostics | D95: As a patient, enrolling in a package includes and prompts its bundled tests (e.g. DEXA and RMR for body composition). | E95: Retained | F95: Yes | G95: 6 | H95: 6 | K95: Prototype Link
B96: Patient Mobile – Upgrade | C96: Establish Your Baseline | D96: As a Patient, I should see the baseline tests my plan needs with their prices and a “Why?” explanation, be able to select or skip each one, see that skipped tests mean my plan uses averages, and see the total. | E96: New | F96: Yes | G96: 6 | H96: 6 | K96: Prototype Link
B97: Patient Mobile – Upgrade | C97: Schedule Your Tests | D97: As a Patient, I should be able to pick a date and time for each baseline test at its location from the available dates, and confirm my schedule. | E97: New | F97: Yes | G97: 8 | H97: 8 | K97: Prototype Link
B98: Packages | C98: Package progress | D98: As a patient, I can track testing and progress within my package. | E98: Retained | F98: Yes | G98: 6 | H98: 6 | K98: Prototype Link
B99: Packages | C99: Results to record | D99: As the system, package diagnostic results flow into the record and inform AI recommendations. | E99: Retained | F99: Yes | G99: 6 | H99: 6 | K99: Not Req
A100: PATIENT CARE TAP
B101: Patient Mobile – Care | C101: Care Tab | D101: As a Patient, I should be able to browse the care I can buy by category, with what each category includes and its starting price. | E101: New | F101: Yes | G101: 8 | H101: 4 | K101: Prototype Link
B102: Patient Mobile – Care | C102: Category List | D102: As a Patient, I should be able to open a category, such as Laboratory or Devices & wearables, and see each item with a short description and price. | E102: New | F102: Yes | G102: 8 | H102: 4 | K102: Prototype Link
B103: Patient Mobile – Care | C103: Item Details & Order | D103: As a Patient, I should be able to open an item, see its price, what it does and what it can’t tell me, ask Inlay about it(optamized plan), and order and pay for it. | E103: New | F103: Yes | G103: 8 | H103: 8 | K103: Prototype Link
B104: Patient Mobile – Care | C104: Book a Time | D104: As a Patient, I should be able to book a time for a test I’ve paid for by choosing a location, date and time, and get a booking confirmation I can add to my calendar or get directions from. | E104: New | F104: Yes | G104: 8 | H104: 6 | K104: Prototype Link
A105: AI COPILOT (CHAT)
B106: Chat | C106: Ask HOL | D106: As a patient, I can ask questions grounded in my own record. | E106: Retained | F106: Yes | G106: 6 | H106: 6 | K106: Prototype Link
...

Sheet Shared Backend Layers
H1: =sum(H4:H92) | I1: =sum(I4:I92)
A2: Sr | B2: Module | C2: Capability | D2: User Story | E2: Required | F2: Priority | G2: Status | H2: Frontend | I2: Backend | J2: Comments
A3: LHOR — LONGITUDINAL RECORD
B4: Normalization | C4: Normalize inputs | D4: As the system, I normalize labs, wearables, uploads and intake into comparable units and ranges. | E4: Yes | F4: Must Have | G4: Covered | H4: 12 | I4: 24
B5: Normalization | C5: Provenance & original values | D5: As the system, I store each value with source, date, unit, range, status, original + normalized. | E5: Yes | F5: Must Have | G5: Covered | H5: 8 | I5: 16
B6: Normalization | C6: Deduplication | D6: As the system, I deduplicate overlapping records across sources. | E6: Yes | F6: Must Have | G6: Covered | H6: 6 | I6: 12
B7: Record | C7: Longitudinal DB | D7: As the system, I maintain one time-series longitudinal record per patient. | E7: Yes | F7: Must Have | G7: Covered | H7: 12 | I7: 24
B8: Record | C8: 16-entity data model | D8: As the system, I persist the full data model (observation, goal, intervention, alert, etc.). | E8: Yes | F8: Must Have | G8: Covered | H8: 12 | I8: 20
B9: Record | C9: Document store | D9: As the system, I store uploads/reports in private encrypted S3 with a review status. | E9: Yes | F9: Must Have | G9: Covered | H9: 6 | I9: 12
B10: Record | C10: Idempotent imports | D10: As the system, imports are idempotent with reconciliation reports. | E10: Yes | F10: Must Have | G10: Covered | H10: 6 | I10: 12
B11: Provenance | C11: Six provenance labels | D11: As the system, every item carries a provenance label — verified source, clinician documented, patient reported, device derived, AI inferred, physician confirmed — kept visibly distinct. | E11: Yes | F11: Must Have | G11: Covered | H11: 10 | I11: 20
B12: Provenance | C12: No silent AI-to-fact writes | D12: As the system, AI inferences and patient-reported items are never silently converted into verified or physician-confirmed facts. | E12: Yes | F12: Must Have | G12: Covered | H12: 6 | I12: 14
B13: Provenance | C13: Gaps & conflicts disclosed | D13: As the system, I state the period and count of values reviewed, disclose material gaps, and show conflicting values as conflicts until reconciled. | E13: Yes | F13: Must Have | G13: Covered | H13: 8 | I13: 16
B14: Provenance | C14: Assay/unit trend compatibility | D14: As the system, I do not trend values across incompatible units, methods or populations without labeling the limitation. | E14: Yes | F14: Must Have | G14: Covered | H14: 8 | I14: 16
B15: Provenance | C15: Auditable patient corrections | D15: As the system, patient corrections keep the original entry, request, decision and corrected display traceable. | E15: Yes | F15: Must Have | G15: Covered | H15: 6 | I15: 12
A16: AI INTELLIGENCE LAYER
B17: Model | C17: Pre-trained commercial model via API | D17: As the system, I call a pre-trained commercial healthcare model via API (OpenAI/Anthropic); HOL does not train or self-host a model. | E17: Yes | F17: Must Have | G17: Covered | H17: 8 | I17: 16
B18: Orchestration | C18: Context assembly | D18: As the system, I assemble patient context + protocols for each call. | E18: Yes | F18: Must Have | G18: Covered | H18: 12 | I18: 20
B19: Retrieval | C19: Protocol retrieval + grounding | D19: As the system, I retrieve relevant SOPs and ground output in the patient's data. | E19: Yes | F19: Must Have | G19: Covered | H19: 12 | I19: 20
B20: Generation | C20: Report + digest generation | D20: As the system, I generate the optimization report, personalized protocol and physician digest. | E20: Yes | F20: Must Have | G20: Covered | H20: 12 | I20: 20
B21: Generation | C21: Structured outputs | D21: As the system, outputs are structured/constrained and traceable to source. | E21: Yes | F21: Must Have | G21: Covered | H21: 8 | I21: 14
B22: Evaluation | C22: Evaluation harness | D22: As the system, every change is regression-tested against graded clinical cases before shipping. | E22: Yes | F22: Must Have | G22: Covered | H22: 12 | I22: 20
B23: Evaluation | C23: Output versioning | D23: As the system, outputs are versioned so vendor updates can't silently change behavior. | E23: Yes | F23: Must Have | G23: Covered | H23: 6 | I23: 12
B24: Monitoring | C24: Live safety monitoring | D24: As the system, I monitor live outputs for safety incidents with a correction path. | E24: Yes | F24: Must Have | G24: Covered | H24: 6 | I24: 12
B25: Metering | C25: Usage metering | D25: As the system, I meter AI usage against the allotment and flag overage. | E25: Yes | F25: Must Have | G25: Covered | H25: 6 | I25: 10
B26: Evidence | C26: Versioned evidence library | D26: As the system, substantive claims are generated by retrieval from a controlled, versioned source library, not from model memory. | E26: Yes | F26: Must Have | G26: Covered | H26: 14 | I26: 26
B27: Evidence | C27: Evidence tiering (A–D + excluded) | D27: As the system, every recommendation retains source, date, evidence tier, population, review date and approving authority; excluded sources cannot justify a recommendation. | E27: Yes | F27: Must Have | G27: Covered | H27: 8 | I27: 16
B28: Evidence | C28: Disagreement handling | D28: As the system, when approved sources disagree I describe the disagreement rather than pick the most aggressive optimization position. | E28: Yes | F28: Must Have | G28: Covered | H28: 4 | I28: 8
... B33: Change control | C33: Regression + staged rollout + rollback | D33: As the system, any change is regression-tested against the clinical safety set, rolled out in stages, and can be rolled back. | E33: Yes | F33: Must Have | G33: Covered | H33: 10 | I33: 20
A34: AI SAFETY & GUARDRAILS
B35: Guardrails | C35: No diagnosis | D35: As the system, I never state a diagnosis; I describe findings and refer to the physician. | E35: Yes | F35: Must Have | G35: Covered | H35: 10 | I35: 16
B36: Guardrails | C36: No medication advice | D36: As the system, I never recommend or adjust medications; I route medication questions to the physician. | E36: Yes | F36: Must Have | G36: Covered | H36: 8 | I36: 12
B37: Guardrails | C37: Route clinical to physician | D37: As the system, I route clinical and symptom questions to the physician. | E37: Yes | F37: Must Have | G37: Covered | H37: 6 | I37: 10
B38: Guardrails | C38: Emergency red-flag rules | D38: As the system, deterministic red-flag rules direct the patient to urgent care. | E38: Yes | F38: Must Have | G38: Covered | H38: 8 | I38: 14
B39: Guardrails | C39: Source citation | D39: As the system, I cite legitimate sources for informational answers. | E39: Yes | F39: Must Have | G39: Covered | H39: 6 | I39: 12
B40: Guardrails | C40: Boundary enforcement | D40: As the system, I keep responses within wellness/lifestyle scope and resist bypass attempts. | E40: Yes | F40: Must Have | G40: Covered | H40: 8 | I40: 14
B41: Guardrails | C41: Lifestyle guidance allowed | D41: As the system, I allow lifestyle and wellness recommendations within bounds. | E41: Yes | F41: Must Have | G41: Covered | H41: 4 | I41: 8
B42: Guardrails | C42: Consult-physician framing | D42: As the system, I append consult-your-physician framing when something is out of the ordinary. | E42: Yes | F42: Must Have | G42: Covered | H42: 4 | I42: 8
A43: CRM / CARE ORCHESTRATION
B44: Member record | C44: 360 member record | D44: As the system, I hold the 360 member record and each patient's journey state. | E44: Yes | F44: Must Have | G44: Covered | H44: 12 | I44: 20
B45: Care loop | C45: Assess-plan-act-monitor-refine | D45: As the system, I run the care loop including the physician sign-off step. | E45: Yes | F45: Must Have | G45: Covered | H45: 12 | I45: 20
B46: Routing | C46: Sign-off routing | D46: As the system, I route each report to the physician for review and release on sign-off. | E46: Yes | F46: Must Have | G46: Covered | H46: 8 | I46: 14
B47: Routing | C47: Abnormal-finding routing | D47: As the system, I route flagged findings to patient and physician promptly. | E47: Yes | F47: Must Have | G47: Covered | H47: 8 | I47: 14
B48: Engagement | C48: Automation | D48: As the system, I run reminders, nudges, milestones and contextual add-on prompts. | E48: Yes | F48: Must Have | G48: Covered | H48: 10 | I48: 14
B49: Scoring | C49: Scoring engine | D49: As the system, I compute overall and domain scores, rules-based and versioned. | E49: Yes | F49: Must Have | G49: Covered | H49: 12 | I49: 18
B50: Forecast | C50: Forecast engine | D50: As the system, I produce trend forecasts labeled 'forecast, not diagnosis' with confidence. | E50: Yes | F50: Must Have | G50: Covered | H50: 10 | I50: 16
B51: Alerts | C51: Alert / rules engine | D51: As the system, at least 10 deterministic safety/priority rules run and are auditable. | E51: Yes | F51: Must Have | G51: Covered | H51: 10 | I51: 18
B52: Escalation | C52: 5-level escalation matrix | D52: As the system, I route each issue to one of five levels (0 informational, 1 protocol-managed, 2 routine review, 3 prompt review, 4 urgent) by decision required, not by topic. | E52: Yes | F52: Must Have | G52: Covered | H52: 16 | I52: 30
B53: Escalation | C53: Episode-based deduplication | D53: As the system, multiple questions about the same result create one issue, not multiple physician alerts. | E53: Yes | F53: Must Have | G53: Covered | H53: 8 | I53: 16
B54: Escalation | C54: Pending-review awareness | D54: As the system, the chat knows an issue is already queued and tells the patient no duplicate message is needed. | E54: Yes | F54: Must Have | G54: Covered | H54: 4 | I54: 10
B55: Escalation | C55: Cooldown & suppression | D55: As the system, resolved/acknowledged/retest-pending items are not re-alerted unless risk changes. | E55: Yes | F55: Must Have | G55: Covered | H55: 4 | I55: 10
... B57: Escalation | C57: Physician summary standard | D57: As the system, physician review items carry current result, history, related data, meds, patient context, evidence, confidence and the exact decision — never a raw transcript. | E57: Yes | F57: Must Have | G57: Covered | H57: 8 | I57: 14
A58: DATA & INTEGRATION LAYER
B59: Integration bridge | C59: Unified EHR API | D59: As the system, I provide one integration bridge exposing a single unified API for all connected EHRs. | E59: Yes | F59: Must Have | G59: Covered | H59: 16 | I59: 28
B60: EHR connector | C60: Epic (FHIR) | D60: As the system, I connect to Epic via patient-authorized FHIR APIs. | E60: Yes | F60: Must Have | G60: Covered | H60: 12 | I60: 24
B61: EHR connector | C61: Cerner / Oracle (FHIR) | D61: As the system, I connect to Cerner (Oracle Health) via patient-authorized FHIR APIs. | E61: Yes | F61: Must Have | G61: Covered | H61: 10 | I61: 20
B62: EHR connector | C62: athenahealth (FHIR) | D62: As the system, I connect to athenahealth via patient-authorized FHIR APIs. | E62: Yes | F62: Must Have | G62: Covered | H62: 10 | I62: 20
B63: EHR connector | C63: Extensible connectors | D63: As the system, I add new EHR connectors within the bridge without changing the client-facing API. | E63: Yes | F63: Must Have | G63: Covered | H63: 6 | I63: 14
B64: Normalization | C64: FHIR normalization | D64: As the system, I normalize each EHR FHIR response into the HOL unified data model. | E64: Yes | F64: Must Have | G64: Covered | H64: 10 | I64: 20
B65: Multi-hospital | C65: Multiple authorizations | D65: As the system, I support multiple hospital authorizations per patient into one record. | E65: Yes | F65: Must Have | G65: Covered | H65: 8 | I65: 14
B66: Multi-hospital | C66: Same-EHR account linking | D66: As the system, I support linking multiple accounts on one EHR (e.g. Epic MyChart Central) where available. | E66: Yes | F66: Must Have | G66: Covered | H66: 6 | I66: 12
B67: HIE / TEFCA | C67: Exchange option (evaluate) | D67: As the system, I can optionally retrieve records via an HIE / TEFCA network for providers not directly integrated. | E67: Yes | F67: Must Have | G67: Covered | H67: 0 | I67: 0
B68: Auto-ingestion | C68: Automatic ingestion | D68: As the system, I ingest new results into the record automatically with no patient action. | E68: Yes | F68: Must Have | G68: Covered | H68: 6 | I68: 14
B69: Auto-ingestion | C69: Real-time webhook push | D69: As the system, I subscribe to EHR webhooks and ingest new data in real time where supported. | E69: Yes | F69: Must Have | G69: Covered | H69: 8 | I69: 18
B70: Auto-ingestion | C70: Polling fallback | D70: As the system, I fall back to scheduled polling for EHRs without webhook support. | E70: Yes | F70: Must Have | G70: Covered | H70: 6 | I70: 12
... B74: Partners | C74: Partner connections | D74: As the system, I connect to DEXA, payments, notification and identity partners. | E74: Yes | F74: Must Have | G74: Covered | H74: 8 | I74: 16
A75: IDENTITY, ACCESS & MULTI-TENANCY
B76: Identity | C76: Authentication | D76: As the system, I authenticate all six roles; MFA for clinicians. | E76: Yes | F76: Must Have | G76: Covered | H76: 12 | I76: 16
B77: Access | C77: RBAC | D77: As the system, I enforce role-based access across all surfaces. | E77: Yes | F77: Must Have | G77: Covered | H77: 8 | I77: 16
B78: Tenancy | C78: Tenant isolation | D78: As the system, I isolate each practice's data as its own tenant. | E78: Yes | F78: Must Have | G78: Covered | H78: 12 | I78: 20
C79: White-label config | D79: As the system, I support per-practice white-label branding. | E79: Yes | F79: Must Have | G79: Covered | H79: 8 | I79: 12
A80: NOTIFICATIONS (DELIVERY ENGINE)
B81: Notifications | C81: Multi-channel delivery | D81: As the system, I deliver push, email and SMS alerts across all portals (no PHI in email/SMS). | E81: Yes | F81: Must Have | G81: Covered | H81: 6 | I81: 12
A82: PLATFORM FOUNDATIONS — SECURITY, COMPLIANCE & RESILIENCE
B83: Security | C83: Encryption & secrets | D83: As the system, all PHI is encrypted at rest (AES-256) and in transit (TLS 1.2+). | E83: Yes | F83: Must Have | G83: Covered | H83: 8 | I83: 16
B84: Audit | C84: Immutable audit trail | D84: As the system, every view/edit/AI output/approval/export is logged immutably. | E84: Yes | F84: Must Have | G84: Covered | H84: 8 | I84: 16
B85: Resilience | C85: Backups & DR | D85: As the system, I run encrypted backups with a tested disaster-recovery plan. | E85: Yes | F85: Must Have | G85: Covered | H85: 6 | I85: 14
B86: Compliance | C86: SOC 2 posture | D86: As a system admin, I maintain a SOC 2 Type II-ready posture. | E86: Yes | F86: Must Have | G86: Covered | H86: 8 | I86: 16
A87: BILLING ENGINE
B88: Billing engine | C88: Payment processing | D88: As the system, I process payments securely via the payment provider (PCI-compliant). | E88: Yes | F88: Must Have | G88: Covered | H88: 10 | I88: 20
B89: Billing engine | C89: Subscription lifecycle | D89: As the system, I manage subscription lifecycle (renewals, proration, dunning). | E89: Yes | F89: Must Have | G89: Covered | H89: 10 | I89: 18
B90: Billing engine | C90: Usage metering | D90: As the system, I meter AI and service usage for billing. | E90: Yes | F90: Must Have | G90: Covered | H90: 6 | I90: 12
B91: Billing engine | C91: Revenue-share settlement engine | D91: As the system, I compute practice/HOL revenue split and physician fees. | E91: Yes | F91: Must Have | G91: Covered | H91: 8 | I91: 16
B92: Billing engine | C92: Ledger & audit | D92: As the system, I keep an auditable billing ledger of all transactions. | E92: Yes | F92: Must Have | G92: Covered | H92: 6 | I92: 14
A93: CLINICAL POLICY ENGINE
B94: Clinical Policy Engine | C94: Policy engine outside the LLM | D94: As the system, I enforce allowed actions, thresholds, special-population rules and routing in a policy engine the LLM cannot override. | E94: Yes | F94: Must Have | G94: Covered | H94: 24 | I94: 44
B95: Clinical Policy Engine | C95: Action-category control | D95: As the system, the LLM cannot change the action category (education / protocol / clinical decision / urgent) — only the policy engine decides. | E95: Yes | F95: Must Have | G95: Covered | H95: 10 | I95: 20
B96: Clinical Policy Engine | C96: Safety validator | D96: As the system, I validate every AI answer for claims, medication boundaries, urgency, contradictions and prohibited content, and block/repair/escalate before delivery. | E96: Yes | F96: Must Have | G96: Covered | H96: 14 | I96: 26
B97: Clinical Policy Engine | C97: Architectural hard stops | D97: As the system, the LLM cannot write to the verified record, send physician alerts, change urgency, order tests, change meds or trigger purchases without policy-engine authorization. | E97: Yes | F97: Must Have | G97: Covered | H97: 8 | I97: 18
A98: COMMERCIAL FIREWALL
B99: Commercial firewall | C99: Clinical/commercial separation | D99: As the system, the clinical recommendation engine is technically and organizationally separated from marketplace ranking and advertising. | E99: Yes | F99: Must Have | G99: Covered | H99: 12 | I99: 24
B100: Commercial firewall | C100: No revenue-driven recommendations | D100: As the system, margin, commission, inventory, partner status or sponsorship never influence clinical ranking. | E100: Yes | F100: Must Have | G100: Covered | H100: 6 | I100: 12
B101: Commercial firewall | C101: Conflict disclosure + audit | D101: As the system, when HOL sells an item it recommends, patient and physician see a conflict disclosure, and each recommendation is audited against evidence vs. purchase. | E101: Yes | F101: Must Have | G101: Covered | H101: 8 | I101: 14
E103: Yes | H103: =SUMIFS(H3:H101,E3:E101,E103) | I103: =SUMIFS(I3:I101,E3:E101,E103)
F104: Must Have | H104: =SUMIFS(H3:H101,F3:F101,F104) | I104: =SUMIFS(I3:I101,F3:F101,F104)
F105: Could Have | H105: =SUMIFS(H4:H102,F4:F102,F105) | I105: =SUMIFS(I4:I102,F4:F102,F105)
F106: Nice To have | H106: =SUMIFS(H5:H103,F5:F103,F106) | I106: =SUMIFS(I5:I103,F5:F103,F106)

Sheet Coach Portal
H1: =sum(H4:H21) | I1: =sum(I4:I21)
A2: Sr | B2: Module | C2: Capability | D2: User Story | E2: Required | F2: Priority | G2: STATUS | H2: Frontend | I2: Backend | J2: Comments
A3: ACCESS
B4: Auth | C4: Login & MFA | D4: As a coach, I can log in securely with MFA. | E4: Yes | F4: Nice To have | G4: Removed | H4: 4 | I4: 4
B5: Auth | C5: Scoped access (RBAC) | D5: As a coach, I can only see wellness data for my assigned patients — no clinical record, alerts, or sign-off. | E5: Yes | F5: Nice To have | G5: Removed | H5: 4 | I5: 6
A6: PATIENT CONTEXT
B7: Context | C7: Assigned patient list | D7: As a coach, I can see the list of patients assigned to me. | E7: Yes | F7: Nice To have | G7: Removed | H7: 4 | I7: 4
B8: Context | C8: Physician-approved goals | D8: As a coach, I can view the patient's physician-approved goals. | E8: Yes | F8: Nice To have | G8: Removed | H8: 4 | I8: 4
B9: Context | C9: Lifestyle plan | D9: As a coach, I can view the patient's approved lifestyle plan. | E9: Yes | F9: Nice To have | G9: Removed | H9: 4 | I9: 4
B10: Context | C10: Adherence view | D10: As a coach, I can view the patient's adherence and check-ins. | E10: Yes | F10: Nice To have | G10: Removed | H10: 4 | I10: 4
A11: SCHEDULING
B12: Scheduling | C12: View & manage sessions | D12: As a coach, I can view and manage my coaching sessions. | E12: Yes | F12: Nice To have | G12: Removed | H12: 8 | I12: 8
B13: Scheduling | C13: Availability | D13: As a coach, I can set my availability. | E13: Yes | F13: Nice To have | G13: Removed | H13: 8 | I13: 8
A14: MESSAGING
B15: Messaging | C15: Secure patient messaging | D15: As a coach, I can securely message my assigned patients. | E15: Yes | F15: Nice To have | G15: Removed | H15: 8 | I15: 8
B16: Messaging | C16: Wellness boundary | D16: As a coach, messaging stays within the wellness boundary — no clinical advice. | E16: Yes | F16: Nice To have | G16: Removed | H16: 8 | I16: 8
A17: SESSION NOTES
B18: Notes | C18: Add session notes | D18: As a coach, I can record coaching session notes. | E18: Yes | F18: Nice To have | G18: Removed | H18: 6 | I18: 6
B19: Notes | C19: View note history | D19: As a coach, I can view my past notes for a patient. | E19: Yes | F19: Nice To have | G19: Removed | H19: 6 | I19: 6
A20: NOTIFICATIONS
B21: Notifications | C21: Session & message alerts | D21: As a coach, I receive alerts for upcoming sessions and new patient messages (no PHI). | E21: Yes | F21: Nice To have | G21: Removed | H21: 4 | I21: 4
E23: Yes | H23: =SUMIFS(H3:H21,E3:E21,E23) | I23: =SUMIFS(I3:I21,E3:E21,E23)
F24: Must Have | H24: =SUMIFS(H3:H21,F3:F21,F24) | I24: =SUMIFS(I3:I21,F3:F21,F24)
F25: Could Have | H25: =SUMIFS(H4:H22,F4:F22,F25) | I25: =SUMIFS(I4:I22,F4:F22,F25)
F26: Nice To have | H26: =SUMIFS(H3:H23,F3:F23,F26) | I26: =SUMIFS(I3:I23,F3:F23,F26)

Sheet Integrations
F1: =SUM(F3:F9)
A2: Sr | B2: Integration | C2: Preferred Vendors | D2: Required | E2: Priority | F2: BE | G2: FE | H2: Comments
B3: SMS | C3: Twilio | D3: Yes | E3: Must Have | F3: 32
B4: Email | C4: Sendgrid | D4: Yes | E4: Must Have | F4: 32
B5: Werables | C5: Terra | D5: Yes | E5: Must Have | F5: 60
B6: DEXA | C6: BodySpec/ Fitnescity | D6: Yes | E6: Must Have | F6: 60
B7: AI model | C7: OpenAI / Anthropic | D7: Yes | E7: Must Have | F7: 60
B8: Payments | C8: Stripe | D8: Yes | E8: Must Have | F8: 32
B9: Labs | C9: Quest | D9: Yes | E9: Must Have | F9: 40
B10: Firebase | C10: Firebase | G10: 12
D14: Yes | F14: =SUMIFS(F3:F9,D3:D9,D14)
E15: Must Have | F15: =SUMIFS(F3:F9,E3:E9,E15)
E16: Could Have | F16: =SUMIFS(F3:F10,E3:E10,E16)
E17: Nice To have | F17: =SUMIFS(F3:F13,E3:E13,E17)

Sheet EHR Integration
A1: Types | B1: Resource Type | C1: Method | D1: FHIR Resource | E1: Resource Use | F1: Required | G1: Epic | I1: Cerner | K1: Meditech
G2: API Link | I2: API Link | K2: API Link
A3: Patient | B3: Search Patient | C3: Get | D3: Patient | E3: Fetch Filter Patient | G3: Yes | H3: 6 | I3: Yes | J3: 6 | K3: Yes | L3: 8
B4: Read Patient | C4: Get | D4: Patient | E4: Read specific patient | G4: Yes | H4: 6 | I4: Yes | J4: 6 | K4: Yes | L4: 8
B5: Create Patient | C5: Post | D5: Patient | E5: Create patient | G5: Yes | H5: 6 | I5: Yes | J5: 6 | K5: No
B6: Patient Family History | C6: Get | D6: FamilyMemberHistory | E6: Read patient family | G6: Yes | H6: 6 | I6: No | K6: No
B7: Search Patient Consent | C7: Get | D7: Patient Consent | E7: Read patient Consent | G7: Yes | H7: 6 | I7: Yes | J7: 6 | K7: No
A9: Clinical Data | B9: Search Allergy | C9: Get | D9: AllergyIntolerance | E9: Fetch Patient Allergy | G9: Yes | H9: 6 | I9: Yes | J9: 6 | K9: Yes | L9: 8
B10: Create Allergy | C10: Post | D10: AllergyIntolerance | E10: Create allergy | G10: Yes | H10: 6 | I10: Yes | J10: 6 | K10: No
B11: Search Condition | C11: Get | D11: Condition | E11: Fetch Patient Condition | G11: Yes | H11: 6 | I11: Yes | J11: 6 | K11: Yes | L11: 8
B12: Create Condition | C12: Post | D12: Condition | E12: Create Condition | G12: Yes | H12: 6 | I12: Yes | J12: 6 | K12: No
B13: Search MedicationRequest | C13: Get | D13: MedicationRequest | E13: Fetch Patient MedicationRequest | G13: Yes | H13: 6 | I13: Yes | J13: 6 | K13: Yes | L13: 8
B14: Create MedicationRequest | C14: Get | D14: MedicationRequest | E14: Create MedicationRequest | G14: No | I14: Yes | J14: 6 | K14: No
A16: Vitals | B16: Search Observation | C16: Get | D16: Observation | E16: Fetch Patient Observation | G16: Yes | H16: 6 | I16: Yes | J16: 6 | K16: Yes | L16: 8
B17: Create Observation | C17: Post | D17: Observation | E17: Create Patient Observation | G17: Yes | H17: 6 | I17: Yes | J17: 6 | K17: No
A19: Appointment | B19: Search Patient Appointment | C19: Post | D19: Appointment | E19: Fetch Patient Appointment | G19: Yes | H19: 6 | I19: Yes | J19: 6 | K19: Yes | L19: 8
B20: Create Appointment | C20: Post | D20: Appointment/$book | E20: Create Appointment for Patient | G20: Yes | H20: 6 | I20: Yes | J20: 6 | K20: No
B21: Search Provider Appointment | C21: Get | D21: Appointment | E21: Fetch Provider Appointment | G21: No | I21: Yes | J21: 6 | K21: No
A23: Availability / Slot | B23: Search Slot | C23: Get | D23: Appointment/$find | E23: Fetch slot for booking appointment | G23: Yes | H23: 6 | I23: Yes | J23: 6 | K23: No
B24: Create Slot | C24: Post | D24: Appointment/$find | E24: Create new slot | G24: No | I24: No | K24: No
A26: Encounter | B26: Search Patient Encounter | C26: Get | D26: Encounter | E26: Fetch Patient Encounter | G26: Yes | H26: 6 | I26: Yes | J26: 6 | K26: Yes | L26: 8
B27: Create Patient Encounter | C27: Post | D27: Encounter | E27: Create Patient Encounter | G27: No | I27: Yes | J27: 6 | K27: No
A29: SOAP Note (Clinical Notes) | B29: Search Patient SOAP Note | C29: Get | D29: DocumentRefernece | E29: Fetch Patient Clinical Notes | G29: Yes | H29: 6 | I29: Yes | J29: 6 | K29: Yes | L29: 8
B30: Create Patient SOAP Note | C30: Post | D30: DocumentRefernece | E30: Create Patient Clinical Notes | G30: Yes | H30: 6 | I30: Yes | J30: 6 | K30: No
A32: Insurance | B32: Search Patient Insurance | C32: Get | D32: Coverage | E32: Fetch Patient Insurance | G32: Yes | H32: 6 | I32: Yes | J32: 6 | K32: Yes | L32: 8
B33: Create Patient Insurance | C33: Post | D33: Coverage | E33: Create Patient Insurance | G33: No | I33: Yes | J33: 6 | K33: No
A35: Provider | B35: Search Provider | C35: Get | D35: Practitioner | E35: Fetch Practitioner by firstName | G35: Yes | H35: 6 | I35: Yes | J35: 6 | K35: Yes | L35: 8
B36: Create Provider | C36: Post | D36: Practitioner | E36: Create Practitioner | G36: No | I36: Yes | J36: 6 | K36: No
A38: Location | B38: Search Location | C38: Get | D38: Location | E38: Fetch Location | G38: Yes | H38: 6 | I38: Yes | J38: 6 | K38: Yes | L38: 8
B39: Create Location | C39: Post | D39: Location | E39: Create Location | G39: No | I39: No | K39: No
A41: Please note that the bulk API takes 30 to 40 minutes on production to return the requested resource response results.
A42: Bulk Resource | B42: Fetch Bulk Resource using Group Id | C42: Get | D42: BulkRequest | E42: Fetch Bulk resource using group Id | G42: Yes | H42: 6 | I42: Yes
H43: =SUM(H2:H42) | J43: =SUM(J2:J42) | L43: =SUM(L2:L42)
